Workbook

Sheet Executive Summary
A1: GeoQueryBench — Combined Group Error Report
A2: Combined from Ziyue, Sarwesh, Chaitanya, Dilani and Thomas | 349 unique allocated query reviews
A4: Executive measure | B4: Result | D4: Reviewer | E4: Assigned | F4: Formal Errors | G4: Notes | H4: Pass | I4: Pass with Note | J4: Fail | K4: Manual Review | L4: Match | M4: Mismatch | N4: Valid Refusal | O4: Reference-only
A5: Combined query rows | B5: =COUNTA('All Query Reviews'!B2:B350) -> 349 | D5: Ziyue | E5: =COUNTIF('All Query Reviews'!$A$2:$A$350,D5) -> 69 | F5: =COUNTIF('Error Register'!$A$2:$A$40,D5) -> 23 | G5: =COUNTIF('Review Notes'!$A$2:$A$59,D5) -> 27 | H5: =COUNTIFS('All Query Reviews'!$A$2:$A$350,D5,'All Query Reviews'!$AG$2:$AG$350,"Pass") -> 19 | I5: =COUNTIFS('All Query Reviews'!$A$2:$A$350,D5,'All Query Reviews'!$AG$2:$AG$350,"Pass with note") -> 27 | J5: =COUNTIFS('All Query Reviews'!$A$2:$A$350,D5,'All Query Reviews'!$AG$2:$AG$350,"Fail") -> 23 | K5: =COUNTIFS('All Query Reviews'!$A$2:$A$350,D5,'All Query Reviews'!$AG$2:$AG$350,"Requires manual semantic review") -> 0 | L5: =COUNTIFS('All Query Reviews'!$A$2:$A$350,D5,'All Query Reviews'!$AG$2:$AG$350,"Match") -> 0 | M5: =COUNTIFS('All Query Reviews'!$A$2:$A$350,D5,'All Query Reviews'!$AG$2:$AG$350,"Mismatch") -> 0 | N5: =COUNTIFS('All Query Reviews'!$A$2:$A$350,D5,'All Query Reviews'!$AG$2:$AG$350,"Valid refusal") -> 0 | O5: =COUNTIFS('All Query Reviews'!$A$2:$A$350,D5,'All Query Reviews'!$AG$2:$AG$350,"Reference-only") -> 0
A6: Formal error-register entries | B6: =COUNTA('Error Register'!B2:B40) -> 39 | D6: Sarwesh | E6: =COUNTIF('All Query Reviews'!$A$2:$A$350,D6) -> 70 | F6: =COUNTIF('Error Register'!$A$2:$A$40,D6) -> 4 | G6: =COUNTIF('Review Notes'!$A$2:$A$59,D6) -> 5 | H6: =COUNTIFS('All Query Reviews'!$A$2:$A$350,D6,'All Query Reviews'!$AG$2:$AG$350,"Pass") -> 60 | I6: =COUNTIFS('All Query Reviews'!$A$2:$A$350,D6,'All Query Reviews'!$AG$2:$AG$350,"Pass with note") -> 5 | J6: =COUNTIFS('All Query Reviews'!$A$2:$A$350,D6,'All Query Reviews'!$AG$2:$AG$350,"Fail") -> 4 | K6: =COUNTIFS('All Query Reviews'!$A$2:$A$350,D6,'All Query Reviews'!$AG$2:$AG$350,"Requires manual semantic review") -> 1 | L6: =COUNTIFS('All Query Reviews'!$A$2:$A$350,D6,'All Query Reviews'!$AG$2:$AG$350,"Match") -> 0 | M6: =COUNTIFS('All Query Reviews'!$A$2:$A$350,D6,'All Query Reviews'!$AG$2:$AG$350,"Mismatch") -> 0 | N6: =COUNTIFS('All Query Reviews'!$A$2:$A$350,D6,'All Query Reviews'!$AG$2:$AG$350,"Valid refusal") -> 0 | O6: =COUNTIFS('All Query Reviews'!$A$2:$A$350,D6,'All Query Reviews'!$AG$2:$AG$350,"Reference-only") -> 0
A7: Review-note entries | B7: =COUNTA('Review Notes'!B2:B59) -> 58 | D7: Chaitanya | E7: =COUNTIF('All Query Reviews'!$A$2:$A$350,D7) -> 70 | F7: =COUNTIF('Error Register'!$A$2:$A$40,D7) -> 2 | G7: =COUNTIF('Review Notes'!$A$2:$A$59,D7) -> 5 | H7: =COUNTIFS('All Query Reviews'!$A$2:$A$350,D7,'All Query Reviews'!$AG$2:$AG$350,"Pass") -> 0 | I7: =COUNTIFS('All Query Reviews'!$A$2:$A$350,D7,'All Query Reviews'!$AG$2:$AG$350,"Pass with note") -> 0 | J7: =COUNTIFS('All Query Reviews'!$A$2:$A$350,D7,'All Query Reviews'!$AG$2:$AG$350,"Fail") -> 0 | K7: =COUNTIFS('All Query Reviews'!$A$2:$A$350,D7,'All Query Reviews'!$AG$2:$AG$350,"Requires manual semantic review") -> 0 | L7: =COUNTIFS('All Query Reviews'!$A$2:$A$350,D7,'All Query Reviews'!$AG$2:$AG$350,"Match") -> 17 | M7: =COUNTIFS('All Query Reviews'!$A$2:$A$350,D7,'All Query Reviews'!$AG$2:$AG$350,"Mismatch") -> 2 | N7: =COUNTIFS('All Query Reviews'!$A$2:$A$350,D7,'All Query Reviews'!$AG$2:$AG$350,"Valid refusal") -> 1 | O7: =COUNTIFS('All Query Reviews'!$A$2:$A$350,D7,'All Query Reviews'!$AG$2:$AG$350,"Reference-only") -> 50
A8: Open error entries | B8: =COUNTIF('Error Register'!J2:J40,"Open") -> 36 | D8: Dilani | E8: =COUNTIF('All Query Reviews'!$A$2:$A$350,D8) -> 70 | F8: =COUNTIF('Error Register'!$A$2:$A$40,D8) -> 3 | G8: =COUNTIF('Review Notes'!$A$2:$A$59,D8) -> 2 | H8: =COUNTIFS('All Query Reviews'!$A$2:$A$350,D8,'All Query Reviews'!$AG$2:$AG$350,"Pass") -> 67 | I8: =COUNTIFS('All Query Reviews'!$A$2:$A$350,D8,'All Query Reviews'!$AG$2:$AG$350,"Pass with note") -> 0 | J8: =COUNTIFS('All Query Reviews'!$A$2:$A$350,D8,'All Query Reviews'!$AG$2:$AG$350,"Fail") -> 3 | K8: =COUNTIFS('All Query Reviews'!$A$2:$A$350,D8,'All Query Reviews'!$AG$2:$AG$350,"Requires manual semantic review") -> 0 | L8: =COUNTIFS('All Query Reviews'!$A$2:$A$350,D8,'All Query Reviews'!$AG$2:$AG$350,"Match") -> 0 | M8: =COUNTIFS('All Query Reviews'!$A$2:$A$350,D8,'All Query Reviews'!$AG$2:$AG$350,"Mismatch") -> 0 | N8: =COUNTIFS('All Query Reviews'!$A$2:$A$350,D8,'All Query Reviews'!$AG$2:$AG$350,"Valid refusal") -> 0 | O8: =COUNTIFS('All Query Reviews'!$A$2:$A$350,D8,'All Query Reviews'!$AG$2:$AG$350,"Reference-only") -> 0
A9: Team members | B9: 5 | D9: Thomas | E9: =COUNTIF('All Query Reviews'!$A$2:$A$350,D9) -> 70 | F9: =COUNTIF('Error Register'!$A$2:$A$40,D9) -> 7 | G9: =COUNTIF('Review Notes'!$A$2:$A$59,D9) -> 19 | H9: =COUNTIFS('All Query Reviews'!$A$2:$A$350,D9,'All Query Reviews'!$AG$2:$AG$350,"Pass") -> 63 | I9: =COUNTIFS('All Query Reviews'!$A$2:$A$350,D9,'All Query Reviews'!$AG$2:$AG$350,"Pass with note") -> 0 | J9: =COUNTIFS('All Query Reviews'!$A$2:$A$350,D9,'All Query Reviews'!$AG$2:$AG$350,"Fail") -> 7 | K9: =COUNTIFS('All Query Reviews'!$A$2:$A$350,D9,'All Query Reviews'!$AG$2:$AG$350,"Requires manual semantic review") -> 0 | L9: =COUNTIFS('All Query Reviews'!$A$2:$A$350,D9,'All Query Reviews'!$AG$2:$AG$350,"Match") -> 0 | M9: =COUNTIFS('All Query Reviews'!$A$2:$A$350,D9,'All Query Reviews'!$AG$2:$AG$350,"Mismatch") -> 0 | N9: =COUNTIFS('All Query Reviews'!$A$2:$A$350,D9,'All Query Reviews'!$AG$2:$AG$350,"Valid refusal") -> 0 | O9: =COUNTIFS('All Query Reviews'!$A$2:$A$350,D9,'All Query Reviews'!$AG$2:$AG$350,"Reference-only") -> 0
A10: Source workbooks | B10: 5 | D10: TOTAL | E10: =SUM(E5:E9) -> 349 | F10: =SUM(F5:F9) -> 39 | G10: =SUM(G5:G9) -> 58 | H10: =SUM(H5:H9) -> 209 | I10: =SUM(I5:I9) -> 32 | J10: =SUM(J5:J9) -> 37 | K10: =SUM(K5:K9) -> 1 | L10: =SUM(L5:L9) -> 17 | ... O10: =SUM(O5:O9) -> 50
A12: Reviewer | B12: Formal Errors | J12: Interpretation notes
A13: Ziyue | B13: =F5 -> 23 | J13: • Outcome labels are preserved from the source reports. • Chaitanya’s Match / Mismatch / Valid refusal / Reference-only results are not recoded as Pass / Fail. • The 39 formal error entries are the union of all five Error Register sheets. • 349 query IDs were combined and no duplicate allocation IDs were found. • Review Notes include both query-specific qualifications and Chaitanya’s scope/methodology notes.
A14: Sarwesh | B14: =F6 -> 4
A15: Chaitanya | B15: =F7 -> 2
A16: Dilani | B16: =F8 -> 3
A17: Thomas | B17: =F9 -> 7

Sheet Error Register
A1: Reviewer | B1: Query ID | C1: Query Type | D1: Method | E1: Issue | F1: Question (EN) | G1: Observed Result / Evidence | H1: Recommended Correction / Next Check | I1: Retest Acceptance | J1: Status | K1: Priority | L1: Source Workbook
A2: Ziyue | B2: CD1-022 | D2: GeoPandas | E2: Global UID de-duplication undercounts samples in overlapping map sheets | F2: Rank the 1:250k map sheets by drilling intensity (holes per 1000 km2) and show the top 10 with both hole count and surface-sample count. | G2: Projected sheet areas, the top-ten density ranking and all unique hole counts reproduced. The sample spatial join contains a small overlap: counting unique UID within each sheet gives WIDGIEMOOLTHA 409,281, while Gold globally drops UID after joining all sheets and reports 409,277. The four samples are arbitrarily assigned away from WIDGIEMOOLTHA; the result depends on spatial-join ordering. This is separate from the Gold ranking, which is driven by hole density and remains correct. Evidence: density test PASS; test_cd1_questions.py::test_cd1_022_counts_unique_samples_within_each_sheet (XFAIL). | H2: Count unique sample UID values within each map sheet, or de-duplicate by the pair (map sheet, UID), rather than globally after the spatial join. Regenerate the result while preserving the independently verified hole-density ranking. | I2: WIDGIEMOOLTHA must contain 409,281 unique surface samples, the count must be deterministic across repeated runs, and the top-ten hole-density ranking must continue to match the independent calculation. | J2: Open | L2: Ziyue_GeoQueryBench_New_Query_Error_Report(1).xlsx
A3: Ziyue | B3: CD1-030 | D3: SQL | E3: SQL counterpart silently switches to a narrower drill-hole population | F3: In SQL, rank the 1:250k map sheets by drilling density (holes per 1000 square kilometres) and return the top ten. | G3: The supplied CSV exactly reproduces when using A_subsurface collar rows: 604,294 collars and the stated top ten. However, metadata calls this the SQL version of CD1-022, whose GeoPandas Gold uses the statewide B_surface drillhole_maxgrade population of 1,836,002 holes. The populations produce materially different rankings and densities: CD1-030 starts WIDGIEMOOLTHA 8,818.8 and KALGOORLIE 8,687.9, whereas CD1-022 starts KALGOORLIE 10,891.7 and WIDGIEMOOLTHA 7,857.4. The source/scope change is not disclosed by the question. Evidence: current-result test PASS; test_cd1_questions.py::test_cd1_030_sql_version_uses_same_drilling_population_as_cd1_022 (XFAIL). | H3: Use the same statewide drill-hole population as the documented CD1-022 counterpart, or explicitly revise the question to state that only the four A-database collar regions are in scope. Regenerate the ranking after the scope is fixed. | I3: The question and implementation must identify the same drilling population. The returned top ten, hole counts and densities must match an independent calculation for that documented population. | J3: Open | L3: Ziyue_GeoQueryBench_New_Query_Error_Report(1).xlsx
A4: Ziyue | B4: CD1-041 | D4: SQL | E4: The requested median nearest-hole distance is missing from the output | F4: How close is the nearest drill hole to each mineral occurrence in the Kalgoorlie box? Give the median and the ten most isolated occurrences. | G4: Independent EPSG:7851 nearest-neighbour distances for 265 mineral occurrences reproduced all ten isolated sites in CD1-041.csv. The median nearest-hole distance is 61.624 m, but neither the Gold SQL nor CSV returns it even though the question explicitly requests the median. Grouping by site_title can also collapse repeated titles. Evidence: top-ten test PASS; test_cd1_questions.py::test_cd1_041_output_includes_requested_median (XFAIL). | H4: Return the independently reproduced median nearest-hole distance together with the ten most isolated occurrences. Preserve a stable occurrence identifier so repeated site titles cannot be collapsed unintentionally. | I4: The result must explicitly report a median nearest-hole distance of approximately 61.624 m and retain the independently verified ten most isolated occurrences. | J4: Open | L4: Ziyue_GeoQueryBench_New_Query_Error_Report(1).xlsx
A5: Ziyue | B5: CD2-036 | D5: SQL | E5: Positive-only filtering excludes documented usable zero Mo values | F5: Is molybdenum measured more often at surface or in drill holes? Give the count of usable values on each side. | G5: The current positive-only Gold result is reproducible, but it conflicts with STUDENT_README's rule that negative assay codes are sentinels and usable values are selected with value >= 0. Gold reports 2,410,326 surface and 416,199 drill values; the documented non-negative rule gives 2,549,435 and 434,795, respectively, because Gold excludes 139,109 surface zeros and 18,596 drill zeros. The question asks for counts only, while Gold also adds an unrequested median column; this is recorded as a schema caveat rather than the primary defect. Evidence: positive-only reproduction PASS; test_cd2_questions.py::test_cd2_036_usable_counts_follow_documented_nonnegative_rule (XFAIL). | H5: Apply the documented usable-value rule value >= 0 on both surface and drill-hole molybdenum fields. Return the requested counts and either remove the unrequested median or label it as additional information. | I5: The regenerated result must include zero values, exclude negative sentinel codes, and report 2,549,435 usable surface values and 434,795 usable drill-hole values. | J5: Open | L5: Ziyue_GeoQueryBench_New_Query_Error_Report(1).xlsx
A6: Ziyue | B6: CD2-043 | D6: SQL | E6: Usable zero sulfur values are excluded and the subsurface native unit is mislabeled | F6: Compare sulphur between the two databases. Careful: it is not stored the same way on both sides. | G6: The current Gold CSV is reproducible, including its defects. First, positive-only filters conflict with the documented non-negative sentinel rule, excluding 112,005 surface zeros and 13,941 subsurface zeros. Second, the subsurface native sulfur unit is s_ppm, but Gold divides the 500 ppm median by 10,000 and reports 0.05 under median_native_unit; 0.05 is percent-equivalent, not the native value. The comparable median_ppm_equiv values are otherwise correctly converted for the positive subset. Evidence: current-output reproduction PASS; test_cd2_questions.py::test_cd2_043_subsurface_native_unit_is_reported_in_ppm (XFAIL); test_cd2_questions.py::test_cd2_043_counts_follow_documented_nonnegative_rule (XFAIL). | H6: Use the documented value >= 0 rule on both sulfur fields. Report the subsurface native median in ppm and place any percent-equivalent conversion in a separately and correctly labelled field. | I6: Zero values must be included, negative sentinel codes excluded, and the subsurface median_native_unit value must be 500 ppm. The value 0.05 may appear only as a clearly labelled percent-equivalent conversion. | J6: Open | L6: Ziyue_GeoQueryBench_New_Query_Error_Report(1).xlsx
A7: Ziyue | B7: CD3-026 | D7: GeoPandas | E7: Equally-nearest drill-hole ties change whether an anomaly is classified as explained | F7: Tested but unexplained: in the Kalgoorlie-Kambalda region, find soil gold anomalies (above 100 ppb) that DO have a drill hole within 1 km, but where that hole returned no significant intercept at all (4 m at 0.5 g/t, 2 m dilution). Report the count, the share of drilled anomalies this represents, and the ten strongest. | G7: The supplied table is internally consistent at 12,760 drilled anomalies and 10,802 unexplained (84.7%), but nearest-hole selection is not deterministic. Sample 10565363 is exactly tied at 124.82 m to holes 4117539, 4317774 and 4331382; the Gold-selected 4331382 is unassayed while tied hole 4117539 has a qualifying >=4 m intercept. Dropping duplicate UID after a tied nearest join therefore changes the scientific classification according to join order. The run logic also permits unlimited consecutive <=2 m dilution rows. Evidence: package/tie test PASS; test_cd3_questions.py::test_cd3_026_nearest_tie_cannot_change_intercept_classification (XFAIL). | H7: Define a deterministic policy for equally-nearest holes, or evaluate all tied holes under an explicitly documented rule. Enforce the intended dilution limit when constructing significant intercepts and regenerate the classifications. | I7: Repeated runs must give the same classification and totals. Sample 10565363 and its three equally-nearest holes must be handled according to the documented tie policy, and the dilution rule must be applied consistently. | J7: Open | L7: Ziyue_GeoQueryBench_New_Query_Error_Report(1).xlsx
A8: Ziyue | B8: CD3-037 | D8: SQL | E8: A 20 km prefilter removes the most remote eligible mineral occurrences | F8: Which gold mineral occurrences have no drill hole within 2 km of them? List the ten with the nearest hole furthest away. | G8: An exact EPSG:7851 KD-tree search found 793 gold sites farther than 2 km from their nearest A collar, including 786 farther than 20 km. Gold first discards every site-hole pair beyond 20 km, so those 786 sites vanish before ranking; it returns only seven sites whose nearest collar happens to fall between 2 and 20 km. Evidence: count test PASS; test_cd3_questions.py::test_cd3_037_gold_is_the_true_top_ten_by_nearest_hole_distance (XFAIL). | H8: Find the true nearest drill hole for every eligible gold occurrence without an upper-distance prefilter, retain occurrences whose nearest hole is farther than 2 km, and rank the ten largest nearest-hole distances. | I8: All 793 occurrences beyond 2 km must remain eligible for ranking, including the 786 whose nearest collar is beyond 20 km, and the returned top ten must match an independent nearest-neighbour calculation. | J8: Open | L8: Ziyue_GeoQueryBench_New_Query_Error_Report(1).xlsx
A9: Ziyue | B9: CD3-038 | D9: SQL | E9: A four-region collar source understates statewide drilling in pegmatites | F9: How many mapped pegmatite bodies are there, and how many of them contain no drill hole at all? | G9: The Gold counts 1,884 pegmatites, 40 drilled and 1,844 undrilled are reproducible only against the four-region A collar table. Using the statewide per-hole maxgrade source identifies 100 pegmatites with drilling and 1,784 without. Because the question says no drill hole at all and does not disclose the narrower source, the Gold count is invalid. Evidence: A-source test PASS; test_cd3_questions.py::test_cd3_038_no_hole_at_all_uses_statewide_drillhole_source (XFAIL). | H9: Use the available statewide drill-hole population when testing whether a pegmatite contains no drill hole at all, or explicitly narrow the question to the four A-database collar regions. | I9: Under the statewide interpretation, the result must report 1,884 pegmatites, 100 with drilling and 1,784 without drilling, matching an independent spatial check. | J9: Open | L9: Ziyue_GeoQueryBench_New_Query_Error_Report(1).xlsx
A10: Ziyue | B10: CD3-047 | D10: SQL | E10: An undisclosed geographic bounding box omits qualifying sampled, undrilled basins | F10: Which sedimentary basins contain surface samples but no drilling? Give basin name and type. | G10: The 27-row CSV is well formed and sorted, but Gold applies an undisclosed longitude 118-123 and latitude -35 to -22 sample bbox. Independent counterexamples outside that box are Kimberley Basin with 10,151 surface samples and zero A collars and Officer Basin Phase 2 with 32 samples and zero A collars; both satisfy the question and are omitted. Evidence: package test PASS; test_cd3_questions.py::test_cd3_047_includes_sampled_undrilled_basins_outside_hidden_bbox (XFAIL). | H10: Remove the hidden longitude/latitude filter and evaluate the stated statewide question, or state the intended regional bounding box explicitly in the question before regenerating the result. | I10: For the statewide question, qualifying basins outside the former box, including Kimberley Basin and Officer Basin Phase 2, must be included and independently reproducible. | J10: Open | L10: Ziyue_GeoQueryBench_New_Query_Error_Report(1).xlsx
A11: Ziyue | B11: CD3-052 | D11: SQL | E11: A four-region drilling source inflates the number of map sheets classified as undrilled | F11: Which map sheets contain mineral occurrences but no drilling? | G11: The 111 sorted sheet names reproduce when drilling is restricted to the four-region A collar table. Under the statewide maxgrade hole source, only PERCIVAL has mineral sites but no hole. The question does not disclose the four-region restriction, so nearly the entire Gold list is contradicted by available statewide drilling. Evidence: A-source test PASS; test_cd3_questions.py::test_cd3_052_no_drilling_uses_statewide_drillhole_source (XFAIL). | H11: Use the available statewide drill-hole source to determine whether each map sheet has drilling, or explicitly disclose the four-region restriction in the question. | I11: Under the statewide interpretation, PERCIVAL must be the only map sheet with mineral occurrences and no drill hole, and the result must match an independent spatial check. | J11: Open | L11: Ziyue_GeoQueryBench_New_Query_Error_Report(1).xlsx
A12: Ziyue | B12: CD3-053 | D12: GeoPandas | E12: The answer uses an undisclosed Kalgoorlie bounding box | F12: Find greenstone belt area that has surface samples but no drilling within 1 km — undrilled prospective ground. | G12: Gold's two rows reproduce inside its hard-coded Kalgoorlie bbox: Eastern Goldfields Superterrane 61,571 and Yilgarn Craton 509 undrilled samples. However, the question asks generally for greenstone-belt area and never names Kalgoorlie or states the coordinates; a hidden geographic scope makes the answer incomplete and non-interpretable. Evidence: scoped reproduction PASS; test_cd3_questions.py::test_cd3_053_question_discloses_its_geographic_scope (XFAIL). | H12: State the Kalgoorlie coordinates in the question if that region is intended, or remove the hidden bounding box and evaluate all greenstone-belt areas covered by the supplied data. | I12: The question and implementation must use the same explicit geographic scope, and all returned counts must match an independent calculation for that scope. | J12: Open | L12: Ziyue_GeoQueryBench_New_Query_Error_Report(1).xlsx
A13: Ziyue | B13: CD3-055 | D13: GeoPandas | E13: Only the p90 ranking is returned although three ranking definitions are claimed | F13: Rank the undrilled ground by how prospective it is. | G13: Independent reconstruction reproduced 34 qualifying same-cell/no-collar cells and the supplied 15 rows ordered by p90 Au. But Gold says three ranking definitions are presented while selecting only the p90 top 15: this omits three cells from the top 15 by maximum and eight from the top 15 by density. A no-collar 5 km cell is also not equivalent to distance-based undrilled ground, and the Kalgoorlie bbox and ranking choice are unstated. Evidence: p90 table PASS; test_cd3_questions.py::test_cd3_055_represents_each_declared_top_fifteen_ranking (XFAIL). | H13: Return a separate top-fifteen list for every declared prospectivity measure, or state that p90 Au is the sole ranking criterion. Also disclose the geographic scope and define whether undrilled means no collar in the cell or no nearby drilling by distance. | I13: Every declared ranking must include its complete deterministic top fifteen without silently omitting cells selected by maximum Au or density. The candidate population and undrilled definition must be explicit and independently reproducible. | J13: Open | L13: Ziyue_GeoQueryBench_New_Query_Error_Report(1).xlsx
... A28: Sarwesh | B28: NS3-026 | D28: geopandas | E28: Gold code cannot execute under the assigned validator; batch summary misreports the failure as PASS_EXECUTION. | F28: Has drilling moved closer to known deposits over time? For holes surveyed in each year from 2016, compute the median distance from the collar to the nearest MINEDEX mineral site. | G28: The batch summary records exit_code 0 / PASS_EXECUTION with an empty output_file field, but the log itself shows 'NameError: name \'con\' is not defined'. The gold code opens with con.execute("SELECT DISTINCT s.hole_id, ...") expecting a DuckDB connection, but the question is tagged task=geopandas and run through validate_geopandas.py, which never imports duckdb or defines con anywhere in its source (confirmed by reading the validator); only validate_sql.py creates that connection, and its execute_gold() only accepts a pure SQL string, not this mixed Python/SQL gold code. Separately, validate_geopandas.py's exception handler never calls sys.exit(1) on gold-code failure, so $LASTEXITCODE stays 0 regardless. No other geopandas-task log in this assigned set showed this masked-failure pattern. | H28: Either give validate_geopandas.py a DuckDB connection object in its execution namespace so hybrid SQL/GeoPandas gold code like this can run, or reclassify NS3-026 to a validator that already provides one. Separately, add sys.exit(1) to validate_geopandas.py's gold-code-failure exception handler so failures are never reported as PASS_EXECUTION. | I28: NS3-026 must execute successfully and produce an NS3-026_rerun.csv under whichever validator is assigned to it, and the batch summary's exit code must be non-zero for any future gold-code execution failure under validate_geopandas.py. | J28: Open | L28: Sarwesh_GeoQueryBench_New_Query_Error_Report(1).xlsx
A29: Chaitanya | B29: CD2-018 | C29: CD-2 | D29: python | E29: Regional bounding-box counts differ from supplied gold. | G29: R4 64,164 vs 64,514; R2 208,355 vs 208,366; R1 534,979 vs 534,994; R3 1,300 vs 1,302. Rerun used collar-coordinate extents as each region’s box. | H29: Confirm intended region geometries/bounds and rerun; retain supplied gold counts until confirmed. | J29: Open | K29: High | L29: GeoQueryBench_Chaitanya_Error_Report_Reference_Style(1).xlsx
A30: Chaitanya | B30: NS4-017 | C30: NS-4 | D30: python | E30: Oxide-total QC summary differs materially from supplied gold. | G30: Rerun: 13,779 within 95–105; 35,328 below 95; 141 above 105; median −9,904.49. Gold: 27,050 within; 22,026 below; 8 above; median 98.01. | H30: Confirm sentinel/missing-value handling and iron-oxide field definition, then regenerate. Keep gold as current reference pending clarification. | J30: Open | K30: High | L30: GeoQueryBench_Chaitanya_Error_Report_Reference_Style(1).xlsx
A31: Dilani | B31: CD2-029 | D31: sql | E31: Missing bore identifiers | F31: In SQL, for each groundwater bore with gold above 50 ng/L, find the distance in metres to the nearest gold MINEDEX site. | G31: Fail: the spatial distance calculation reproduces, but bore_name is null in all 21 rows. The output therefore does not identify each groundwater bore as asked. Use site_code or analysis_id as the bore identifier, optionally retaining bore_name. | H31: Return a populated site_code or analysis_id, retaining bore_name if useful. Confirm the identifier represents the requested bore. | I31: Rerun and confirm all 21 records have an appropriate non-null identifier and unchanged validated distances. | J31: Open — no closure recorded | L31: GeoQueryBench_New_Query_Error_Report(1).xlsx
A32: Dilani | B32: CD4-026 | D32: viz | E32: NumPy condition type error | F32: Map the Kalgoorlie-Kambalda region showing soil gold anomalies coloured by whether the nearest hole within 1 km returned a significant intercept (4 m at 0.5 g/t), no intercept, or has no hole nearby at all, over a grey backdrop of all drilling. | G32: Fail executability: the supplied code raises a NumPy TypeError because the second np.select condition is not a strict Boolean array. Adding .astype(bool) after fillna(False) makes it run and reproduces the supplied map at 98.6% perceptual-hash similarity; the spatial and classification logic otherwise match. | H32: Convert the affected condition after fillna(False) to a strict Boolean array using .astype(bool). | I32: Run the original environment and supported target environment. Confirm execution and inspect map categories, legend and spatial placement. | J32: Open — no closure recorded | L32: GeoQueryBench_New_Query_Error_Report(1).xlsx
A33: Dilani | B33: NS1-027 | D33: sql | E33: Duplicate specimen rows | F33: Interrogate the WACHEM reference suite for specimens whose silica content exceeds 70 weight percent; return the specimen identifier, lithological designation and the SiO2 figure. | G33: Fail: the supplied and independently reproduced outputs agree, but the returned specimen list contains 67 exact duplicate rows. Use SELECT DISTINCT (or establish a documented assay-level key) to return each specimen/value combination once. | H33: Confirm intended output grain. Use SELECT DISTINCT for unique specimen/value combinations, or retain a documented assay-level key for separate records. | I33: Rerun and verify duplicate count at the agreed output grain. Preserve valid distinct assays. | J33: Open — no closure recorded | L33: GeoQueryBench_New_Query_Error_Report(1).xlsx
A34: Thomas | B34: NS4-041 | D34: SQL | E34: Incorrect/internally inconsistent Eu-anomaly formula | F34: Compute the light-to-heavy rare earth ratio (La/Yb) and the europium anomaly for the WA geochemistry samples, and summarise their distributions. | G34: The supplied result is reproducible, but the code comment states that Eu/Eu* normally uses Sm_n and Gd_n and that Sm and Nd will be used because Gd is unavailable. The implemented expression instead uses eu_n / sqrt(sm_n * la_n). Nd is not used at all, despite its normalisation value being documented. Therefore median_eu_anomaly = 0.410 and n_negative_eu_anomaly = 16,297 are based on a formula inconsistent with the stated method. | H34: Confirm the intended Gd-free Eu-anomaly approximation with the client/domain expert and implement that formula consistently. If the intended approximation uses Nd, include and normalise nd_ppm and replace the unintended La term. Regenerate the gold result afterward. | I34: The corrected query must use the agreed Eu-anomaly definition consistently, rerun successfully on the frozen dataset, and the regenerated supplied result must match an independent rerun. | J34: Open | L34: Thomas_GeoQueryBench_New_Query_Error_Report(1).xlsx
A35: Thomas | B35: NS4-051 | D35: SQL | E35: Output aggregation does not identify requested samples, and the R-premise geological classification is unsupported. | F35: Find the surface samples where nickel exceeds 10 percent by weight — those would be massive sulphide. | G35: The >100,000 ppm threshold is correctly implemented and 3,175 qualifying records are represented across four media (2,626 soil, 409 shallow_drill, 138 rock_chip and 2 stream_sed). However, the query groups these records by medium rather than returning the individual samples requested. It also cannot establish from Ni concentration alone that these records are massive sulphide; extreme maxima reach 1,000,000 ppm (100 wt%), which the gold-code comment itself identifies as requiring record-level checking. | H35: Return the individual qualifying sample identifiers, Ni values and relevant sample/location information for Ni >100,000 ppm. Treat “massive sulphide” as an unsupported premise unless an appropriate geological/mineralogical field independently establishes that classification, and flag implausibly high values for data-quality review. | I35: The corrected result identifies the individual samples exceeding 100,000 ppm Ni and does not infer massive-sulphide classification solely from Ni concentration unless supported by independent dataset evidence. | J35: Open | L35: Thomas_GeoQueryBench_New_Query_Error_Report(1).xlsx
A36: Thomas | B36: CD2-016 | D36: geopandas | E36: Non-deterministic handling of equally-nearest routine samples changes the reported Cu correlation. | F36: Two sources of truth: where a WACHEM reference sample sits within 100 m of a routine surface sample, how well do their copper values agree? Report the correlation and the median absolute difference. | G36: The nearest join returns 7,190 rows for 4,917 distinct WACHEM samples. 1,261 WACHEM samples have multiple equally-nearest matches, and 466 of those have different routine Cu values. Applying drop_duplicates('wid') therefore selects an arbitrary tied match. The rerun gives r = 0.1291 versus supplied r = 0.1602; n_pairs = 4,917 and median absolute difference = 14.0 ppm remain unchanged. | H36: Define an explicit deterministic policy for equally-nearest routine samples, such as a documented stable secondary-key tie-break or an aggregation across tied nearest samples, then regenerate the gold result. | I36: Repeated execution under the documented tie policy must return the same WACHEM-routine pairing and correlation, and the supplied result must match the regenerated deterministic result. | J36: Open | L36: Thomas_GeoQueryBench_New_Query_Error_Report(1).xlsx
A37: Thomas | B37: CD2-025 | D37: geopandas | E37: Undefined tie handling for equally-nearest drill holes causes unstable Au-agreement classification; invalid/sentinel hole maximum grades may also enter the classification. | F37: Take the strongest surface gold spots in soil (over 100 ppb). For each, check whether the closest hole within a kilometre also came back rich in gold, at least 1 gram per tonne. Summarise how many agree, how many disagree, and how many have nothing drilled nearby. | G37: The rerun returns 14,506 both_anomalous, 81,377 surface_only and 66,598 no_hole_within_1km, versus supplied counts of 14,594, 81,289 and 66,598. Of 95,883 anomalies with a nearby hole, 19,503 have multiple equally-nearest holes; 3,879 have different maximum Au values and 229 cross the 1 g/t threshold. Deterministic tie policies produce different both_anomalous counts (14,494 using smallest hole_row_id, 14,678 using ANY tied hole ≥1 g/t, and 14,449 requiring ALL tied holes ≥1 g/t). A -9999 hole_max_au value was also observed among tied matches. | H37: Define and document a deterministic policy for equally-nearest holes, filter or otherwise handle invalid/sentinel drill-hole maximum Au values according to dataset metadata, and regenerate the gold result. | I37: Repeated execution must produce identical classifications under the documented tie policy; no invalid/sentinel Au value should be interpreted as a valid <1 g/t result; and the regenerated supplied result must exactly match the deterministic rerun. | J37: Open | L37: Thomas_GeoQueryBench_New_Query_Error_Report(1).xlsx
A38: Thomas | B38: CD4-047 | D38: geopandas | E38: Fault length is assigned to 10 km cells by whole-geometry centroid rather than actual line-grid intersection, and intersecting faults are not clipped to the Kalgoorlie bounding box. | F38: Prepare fault density per 10 km cell in the Kalgoorlie box: total fault length per cell. | G38: The gold result is exactly reproducible, but secondary validation using the same 10 km grid origin and true geometry intersection finds material differences. The gold method includes 11,824.69 km of fault geometry versus 11,311.36 km actually inside the Kalgoorlie box, adding 513.33 km (4.34%) outside the requested area. Across the grid, 149 cells differ by >0.01 km, the maximum absolute difference is 74.95 km and the mean absolute difference is 10.17 km. Only 17 of the gold top-20 cells are also present in the intersection-based top 20. | H38: Clip fault geometries to the exact Kalgoorlie bounding box, construct the 10 km grid, intersect/clip fault lines at cell boundaries, calculate the length of each resulting line segment in EPSG:7851, sum those lengths by cell, and regenerate the top-cell result. | I38: The regenerated result must use only fault length inside the Kalgoorlie box and actual line length within each 10 km cell. Total per-cell length should sum consistently to the clipped fault length (subject only to negligible numerical precision), and the supplied top cells and values must match an independent grid-intersection rerun. | J38: Open | L38: Thomas_GeoQueryBench_New_Query_Error_Report(1).xlsx
A39: Thomas | B39: NS3-020 | D39: geopandas | E39: The supplied gold result is inconsistent with the supplied code and current frozen dataset: WIDGIEMOOLTHA is undercounted by four samples. | F39: Which 10 map sheets have the highest surface-sample density (samples per 1000 km2)? | G39: The supplied result reports 409,277 samples for WIDGIEMOOLTHA, while repeated execution of the supplied code returns 409,281. Secondary validation independently confirms 409,281 distinct samples within WIDGIEMOOLTHA. The sheet has one polygon, there are no boundary-only samples, no WIDGIEMOOLTHA samples belong to another sheet, no sample across the dataset matches more than one distinct map sheet, and drop_duplicates('uid') changes no map-sheet counts. The discrepancy therefore remains a supplied-result reproducibility inconsistency rather than an identified spatial-logic error. | H39: Investigate the provenance of the supplied CD result and regenerate NS3-020.csv from the frozen benchmark dataset and supplied gold code. If 409,277 was generated from a different dataset version or geospatial environment, document and reconcile that difference before regenerating the benchmark artifact. | I39: Executing the documented gold code against the designated frozen dataset must reproduce the supplied result exactly, including the WIDGIEMOOLTHA sample count and derived density, while retaining the semantically correct map-sheet density calculation. | J39: Open | L39: Thomas_GeoQueryBench_New_Query_Error_Report(1).xlsx
A40: Thomas | B40: NS2-054 | D40: viz | E40: The log-probability plot does not actually identify the number of soil-Au populations or determine the threshold between them; P90/P97.5/P99 are fixed percentile references rather than inferred population boundaries. An unstated Au < 100 ppm filter also truncates the high-Au tail. | F40: Draw a log-probability plot of soil gold to identify how many populations are present and where the threshold between them lies. | G40: The supplied and rerun figures are semantically consistent and show the same soil-Au probability curve with P90 = 0.018 ppm, P97.5 = 1.300 ppm and P99 = 3.299 ppm. However, neither the code nor the figure states how many populations are present or identifies a population boundary. The three vertical lines are predetermined percentiles, not thresholds inferred from slope breaks in the probability plot. The code also excludes Au >= 100 ppm without this cutoff being specified in the question. | H40: Use an explicit and documented method to identify population segments or breakpoints in the log-probability distribution, report the resulting number of populations and threshold value(s), and annotate those inferred boundaries on the figure. Remove or justify the <100 ppm upper cutoff. | I40: The regenerated analysis must explicitly report the inferred number of soil-Au populations and the threshold value(s) separating them, with the plotted boundary/boundaries derived from a documented population or breakpoint criterion rather than arbitrary percentile markers. Any upper Au cutoff must be justified or removed. | J40: Open | L40: Thomas_GeoQueryBench_New_Query_Error_Report(1).xlsx

Sheet Review Notes
A1: Reviewer | B1: Query ID / Scope | C1: Topic | D1: Recorded Verdict / Status | E1: Qualification / Review Note | F1: Recommended Follow-up / Action | G1: Evidence File / Test | H1: Source Workbook
A2: Ziyue | B2: CD1-045 | D2: Pass | E2: The reconstructed Kambalda selection contained 14,841 surface samples and 28,421 drill collars. Two distinct layers, count-bearing legend entries, labels, title and equal coordinate aspect rendered successfully; the supplied 966x655 PNG is readable and nonblank. Equal aspect in geographic degrees is only an approximation of physical scale, but it is adequate for the requested qualitative overlay. Evidence: test_cd1_questions.py::test_cd1_045_reconstructs_two_layer_kambalda_map_contract (PASS). | F2: Retain the Gold result and document the recorded qualification so its scope and assumptions are not overstated. | G2: test_cd1_questions.py::test_cd1_045_reconstructs_two_layer_kambalda_map_contract | H2: Ziyue_GeoQueryBench_New_Query_Error_Report(1).xlsx
A3: Ziyue | B3: CD2-023 | D3: Pass | E3: Independent aggregation reproduced the ten largest surface-sample WAMEX reports and verified that the tenth count exceeds the eleventh, so the LIMIT 10 boundary is unambiguous. A left merge with collar counts preserved all ten reports; nine have zero drill holes and report 98358 has 181. Collar row counts equalled distinct hole_id counts. Schema, identifiers, ordering and values matched CD2-023.csv. The nine zero drill-hole counts are valid outputs but remain a cross-dataset coverage or lineage concern. Evidence: test_cd2_questions.py::test_cd2_023_preserves_top_surface_reports_without_drill_holes (PASS). | F3: Retain the current Gold result under the recorded validation verdict. Document the recorded data-quality concern before using the result in downstream quantitative interpretation. | G3: test_cd2_questions.py::test_cd2_023_preserves_top_surface_reports_without_drill_holes | H3: Ziyue_GeoQueryBench_New_Query_Error_Report(1).xlsx
A4: Ziyue | B4: CD2-024 | D4: Pass | E4: Independent recomputation used the inclusive Kambalda box, soil-only surface samples, non-negative Ni values and strict anomaly thresholds. It reproduced 5,895 measured soil samples with 10.04% over 500 ppm and 7,426 measured drill holes with 36.37% over 5,000 ppm. Surface UIDs and hole references were unique, and the GeoParquet CRS was EPSG:7844. The Gold comparison is numerically valid, but the two percentages use different media, thresholds and denominators; deciding whether they are geologically consistent requires domain judgement. Evidence: test_cd2_questions.py::test_cd2_024_recomputes_kambalda_nickel_proportions (PASS). | F4: Retain the current Gold result under the recorded validation verdict. Obtain geological or domain-expert review of the interpretation described in the qualification. | G4: test_cd2_questions.py::test_cd2_024_recomputes_kambalda_nickel_proportions | H4: Ziyue_GeoQueryBench_New_Query_Error_Report(1).xlsx
A5: Ziyue | B5: CD3-021 | D5: Pass | E5: Independent assay merge, percentile ranking and EPSG:9473 nearest-hole search reproduced 113,434 qualifying anomalies, 36,787 undrilled targets and all ten Gold rows. All ten rows form five duplicate-coordinate pairs with different sample IDs, so the numerical answer is valid but the apparent top-ten spatial diversity is misleading. Evidence: test_cd3_questions.py::test_cd3_021_recomputes_composite_scores_and_undrilled_target_count (PASS). | F5: Retain the current Gold result under the recorded validation verdict. Document the recorded data-quality concern before using the result in downstream quantitative interpretation. | G5: test_cd3_questions.py::test_cd3_021_recomputes_composite_scores_and_undrilled_target_count | H5: Ziyue_GeoQueryBench_New_Query_Error_Report(1).xlsx
A6: Ziyue | B6: CD4-021 | D6: Pass | E6: Statewide WAROX counts reproduced as 131,388 mineral and 149,930 rock_type observations. The drillhole layer contains 1,836,002 holes and the code explicitly discloses plotting every thirtieth row (61,201 points), so downsampling is transparent rather than a hidden count claim. The PNG is readable and nonblank. Evidence: test_cd4_questions.py::test_cd4_021_statewide_observation_categories_and_sampling_are_disclosed (PASS). | F6: Retain the current Gold result under the recorded validation verdict. Document the recorded data-quality concern before using the result in downstream quantitative interpretation. | G6: test_cd4_questions.py::test_cd4_021_statewide_observation_categories_and_sampling_are_disclosed | H6: Ziyue_GeoQueryBench_New_Query_Error_Report(1).xlsx
A7: Ziyue | B7: CD4-033 | D7: Pass | E7: The map inputs reproduce 254 pegmatite features intersecting the Kalgoorlie bbox and 373,776 R1 collars; both layers are visible and the PNG is readable. Visual inspection shows that the legend contains only the drill-hole label, because the GeoPandas polygon label is not propagated to Matplotlib's legend. This is a presentation caveat rather than a wrong spatial result. Evidence: test_cd4_questions.py::test_cd4_033_kalgoorlie_pegmatite_and_collar_layers_are_present (PASS), plus visual inspection of CD4-033.png. | F7: Retain the Gold result and document the recorded qualification so its scope and assumptions are not overstated. | G7: test_cd4_questions.py::test_cd4_033_kalgoorlie_pegmatite_and_collar_layers_are_present | H7: Ziyue_GeoQueryBench_New_Query_Error_Report(1).xlsx
A8: Ziyue | B8: CD4-056 | D8: Pass | E8: Independent filtering reproduced 257,967 positive soil Au values below 100 ppm, 373,776 R1 collars and quantile edges 0.000001, 0.0052, 0.012, 0.033, 2.0, 4.7 and 99.35 ppm. The two-panel PNG is readable and the quantile view avoids letting high values dominate the colour scale. The code comment says outlier clipping, but no additional clip occurs after the <100 filter; 99.35 is simply the retained maximum. This wording issue does not invalidate the requested visual comparison. Evidence: test_cd4_questions.py::test_cd4_056_quantile_map_inputs_and_class_edges_are_reproducible (PASS). | F8: Retain the current Gold result under the recorded validation verdict. Document the recorded data-quality concern before using the result in downstream quantitative interpretation. Obtain geological or domain-expert review of the interpretation described in the qualification. | G8: test_cd4_questions.py::test_cd4_056_quantile_map_inputs_and_class_edges_are_reproducible | H8: Ziyue_GeoQueryBench_New_Query_Error_Report(1).xlsx
A9: Ziyue | B9: NS1-021 | D9: Pass | E9: Independent WACHEM filtering reproduced all 202 rows above 0.1 ppm Au and their values. There are only 200 unique sample IDs because two IDs appear twice with different analytical values; the row-level answer is valid, but consumers should not interpret 202 rows as 202 unique samples. Evidence: test_ns1_questions.py::test_ns1_021_recomputes_wachem_gold_above_100_ppb (PASS). | F9: Retain the current Gold result under the recorded validation verdict. Document the recorded data-quality concern before using the result in downstream quantitative interpretation. | G9: test_ns1_questions.py::test_ns1_021_recomputes_wachem_gold_above_100_ppb | H9: Ziyue_GeoQueryBench_New_Query_Error_Report(1).xlsx
A10: Ziyue | B10: NS1-032 | D10: Pass | E10: All 5,407,653 soil rows have bi_ppm at the -9999 sentinel maximum, so no positive measured bismuth value exists. The empty CSV has the requested sample_id and bi_ppm schema and is correct, while also exposing complete absence of usable soil Bi data. Evidence: test_ns1_questions.py::test_ns1_032_empty_soil_bismuth_result_is_supported_by_data (PASS). | F10: Retain the current Gold result under the recorded validation verdict. Document the recorded data-quality concern before using the result in downstream quantitative interpretation. | G10: test_ns1_questions.py::test_ns1_032_empty_soil_bismuth_result_is_supported_by_data | H10: Ziyue_GeoQueryBench_New_Query_Error_Report(1).xlsx
A11: Ziyue | B11: NS2-018 | D11: Pass | E11: Independent date grouping reproduced all five yearly rows: 2002 52/617, 2003 255/592, 2004 325/689, 2005 312/812 and 2006 21/707. Only 965 of 40,581 groundwater rows have a sample_date, so the result is correct for dated analyses but has severe temporal coverage limitations. Evidence: test_ns2_questions.py::test_ns2_018_recomputes_yearly_groundwater_counts_and_tds_medians (PASS). | F11: Retain the current Gold result under the recorded validation verdict. Document the recorded data-quality concern before using the result in downstream quantitative interpretation. | G11: test_ns2_questions.py::test_ns2_018_recomputes_yearly_groundwater_counts_and_tds_medians | H11: Ziyue_GeoQueryBench_New_Query_Error_Report(1).xlsx
A12: Ziyue | B12: NS2-027 | D12: Pass | E12: Independent soil/assay joining produced 3,674,753 non-negative measured Au values, a continuous 95th percentile of 0.068 ppm and 183,412 rows strictly above it, matching Gold's row count and maximum 537,099.97 ppm. The extreme maximum and many very high values warrant source/unit review, but the stated percentile rule is correctly applied. Evidence: test_ns2_questions.py::test_ns2_027_recomputes_strict_top_five_percent_soil_gold_rule (PASS). | F12: Retain the current Gold result under the recorded validation verdict. Document the recorded data-quality concern before using the result in downstream quantitative interpretation. | G12: test_ns2_questions.py::test_ns2_027_recomputes_strict_top_five_percent_soil_gold_rule | H12: Ziyue_GeoQueryBench_New_Query_Error_Report(1).xlsx
A13: Ziyue | B13: NS2-041 | D13: Pass | E13: Independent grouping reproduced the four sample-type row counts and positive-value Al2O3/CaO medians. The n column is the total group row count, not the count with both oxide values usable; this is a clarity/data-coverage note, not a numerical mismatch. Evidence: test_ns2_questions.py::test_ns2_041_recomputes_major_oxide_medians_by_sample_type (PASS). | F13: Retain the current Gold result under the recorded validation verdict. Document the recorded data-quality concern before using the result in downstream quantitative interpretation. | G13: test_ns2_questions.py::test_ns2_041_recomputes_major_oxide_medians_by_sample_type | H13: Ziyue_GeoQueryBench_New_Query_Error_Report(1).xlsx
... A33: Sarwesh | B33: NS5-031 | D33: Pass | E33: Pass with note: the code is fully reproducible (supplied and rerun images are structurally identical), but the plot does not achieve the question's comparison goal. np.logspace(...) bins are combined with ax.hist(..., density=True) normalised by linear bin width; the first log-spaced bin has an extremely small linear width near the data minimum, driving its density to roughly 400,000 in both images while the rock_chip and stream_sed series are compressed to a near-invisible line. The three media's distribution shapes cannot be visually compared as asked. | F33: Normalise by log-bin-width (e.g. plot log10(Au) on a linear-binned density axis) instead of using density=True directly with log-spaced bins. | G33: NS5-031.png | H33: Sarwesh_GeoQueryBench_New_Query_Error_Report(1).xlsx
A34: Chaitanya | B34: CD2-033 | C34: Validated refusal | D34: Validated | E34: Schema check found no reserve/resource estimate fields in supplied mineral_site schema. | F34: Decline reserve tonnes/grade and explain data limitation. | H34: GeoQueryBench_Chaitanya_Error_Report_Reference_Style(1).xlsx
A35: Chaitanya | B35: 50 queries | C35: Independent rerun coverage | D35: Reference-only | E35: Allocation workbook has natural-language questions and method labels; no runnable query implementation was available for these items. | F35: Gold assets and CSV row counts checked; results not independently regenerated. | H35: GeoQueryBench_Chaitanya_Error_Report_Reference_Style(1).xlsx
A36: Chaitanya | B36: All 70 queries | C36: Gold asset / row audit | D36: Checked | E36: All 70 reference files present. All 54 CSV files match Expected Rows; remaining outputs are 15 PNGs and one refusal text file. | F36: Asset and count validation does not establish correctness for reference-only items. | H36: GeoQueryBench_Chaitanya_Error_Report_Reference_Style(1).xlsx
A37: Chaitanya | B37: 19 reruns | C37: Comparison method | D37: Completed | E37: Compared independent output to supplied gold, ignoring row order and applying reference display precision where applicable. | F37: 17 matches and 2 mismatches. | H37: GeoQueryBench_Chaitanya_Error_Report_Reference_Style(1).xlsx
A38: Chaitanya | B38: Chaitanya only | C38: Scope control | D38: Applied | E38: This report includes only Chaitanya’s 70 allocated questions. | F38: Attached example was used only as a layout reference. | H38: GeoQueryBench_Chaitanya_Error_Report_Reference_Style(1).xlsx
A39: Dilani | B39: NS1-036 | D39: Pass | E39: Pass with note: all values answering the question match, including the naive maximum (760,000 ppm), 3,431 values at or above 100 ppm, and the plausible maximum (100 ppm). Only worst_report differs because two reports tie at 397 samples with a 2,000 ppm median and the code has no deterministic tie-breaker. | F39: Agree a deterministic secondary sort or return all tied reports. The report identifier does not match exactly. | G39: NS1-036.csv | H39: GeoQueryBench_New_Query_Error_Report(1).xlsx
A40: Dilani | B40: NS2-044 | D40: Pass | E40: Pass with note: the three-row diagnostic is reproduced. The unfiltered mean (-4,514.0 ppm) is intentionally shown to demonstrate sentinel contamination; the positive-only mean is 95.4 ppm and the additional <100,000 ppm plausibility filter gives 85.0 ppm. No raw sentinel is returned in the result table. | F40: Label the unfiltered mean as a diagnostic. Agree the cleaning rule before presenting one mean as the scientific result. | G40: NS2-044.csv | H40: GeoQueryBench_New_Query_Error_Report(1).xlsx
A41: Thomas | B41: CD1-034 | D41: Pass | E41: Pass with note: the supplied three-row diagnostic result is reproduced exactly. The query correctly distinguishes the Mn commodity code from Mnz (monazite), avoiding the invalid substring match. There are 589 exact-Mn records and 93 records where Mn is one of several primary commodities, giving 682 records containing Mn as a primary commodity. The gold output reports these components separately rather than explicitly returning the combined total requested by the question. | F41: Consider reporting the combined Mn total (682) explicitly while retaining the diagnostic rows to demonstrate why substring matching (%Mn%) is invalid. | G41: CD1-034.csv | H41: Thomas_GeoQueryBench_New_Query_Error_Report(1).xlsx
A42: Thomas | B42: CD1-040 | D42: Pass | E42: Pass with note: the expected empty result is reproduced and the anti-join correctly tests the R-premise. However, surface-sample presence is evaluated only within longitude 118–123 and latitude -35–-22, while the question says “no surface samples at all”. | F42: Confirm that the bounding box represents the complete intended surface-sample coverage for the relevant map sheets; otherwise remove the coordinate filter when testing whether a sheet has no surface samples at all. | G42: CD1-040.csv | H42: Thomas_GeoQueryBench_New_Query_Error_Report(1).xlsx
A43: Thomas | B43: CD4-038 | D43: Pass | E43: Pass with note: the 0.1-degree cell aggregation is reproduced correctly, but the supplied SQL returns only cells with at least 50 records and limits the result to the top 20 by maximum soil Au, whereas the question literally asks for each cell in the Kalgoorlie box. Tied maximum-Au values can also produce non-deterministic relative ordering. | F43: Consider stating the ≥50-sample and top-20 criteria explicitly in the question, or remove HAVING count(*) >= 50 and LIMIT 20 if all populated cells are intended. Add a secondary cell-coordinate tie-breaker if deterministic ordering is required. | G43: CD4-038.csv | H43: Thomas_GeoQueryBench_New_Query_Error_Report(1).xlsx
A44: Thomas | B44: CD4-053 | D44: Pass | E44: Pass with note: the supplied result is reproduced exactly and the recorded and computed palaeovalley areas are consistent. However, the query returns only the 20 largest palaeovalleys by computed area even though the question does not state a top-20 restriction, and the output does not include polygon geometry despite referring to plot-ready outlines. | F44: Clarify the question as requesting the 20 largest palaeovalleys if that is intended. If the output is intended to be directly map-ready, include the palaeovalley geometry (or explicitly state that pv_id is to be joined back to the spatial layer). | G44: CD4-053.csv | H44: Thomas_GeoQueryBench_New_Query_Error_Report(1).xlsx
A45: Thomas | B45: NS1-025 | D45: Pass | E45: Pass with note: the R-para threshold is correctly interpreted as Au >0.1 ppm and all qualifying soil samples are returned. However, the As field contains many negative/sentinel-coded values, including 43,611 occurrences of -9999, 4 of -999 and 163 of -99. These do not invalidate the query because the question does not require valid As measurements only. | F45: Retain all qualifying Au samples for this question, but treat the negative/sentinel-coded As values as unavailable or invalid if the arsenic values are used in subsequent quantitative analysis. Confirm the dataset metadata before treating the Au value 999 ppm as a sentinel. | G45: NS1-025.csv | H45: Thomas_GeoQueryBench_New_Query_Error_Report(1).xlsx
A46: Thomas | B46: NS1-046 | D46: Pass | E46: Pass with note: the quartz-veining text search and rock-name aggregation are reproduced correctly, but the supplied SQL returns only the 15 most frequent rock-name categories although the question does not explicitly request a top-15 result. The 20-character proximity window is also an operational text-search definition, and tied mention counts can produce non-deterministic relative ordering. | F46: State the top-15 criterion explicitly if only the most frequent rock names are intended; otherwise remove LIMIT 15. If deterministic ordering is required, add rock_name as a secondary ORDER BY key. The 20-character quartz/vein proximity rule could also be documented as the intended text-search criterion. | G46: NS1-046.csv | H46: Thomas_GeoQueryBench_New_Query_Error_Report(1).xlsx
A47: Thomas | B47: NS2-043 | D47: Pass | E47: Pass with note: the rock-type frequency ranking is reproduced correctly and the additional geologist-count and concentration diagnostics appropriately address the R-shortcut risk. However, the supplied SQL returns only the 15 most frequently recorded rock types although the question does not explicitly specify a top-15 restriction. | F47: State explicitly that the question requests the top 15 most frequently recorded rock types, or remove LIMIT 15 if all recorded rock types are intended. Retain the geologist-concentration diagnostics because observation frequency should not be interpreted directly as geological abundance. | G47: NS2-043.csv | H47: Thomas_GeoQueryBench_New_Query_Error_Report(1).xlsx
A48: Thomas | B48: NS3-042 | D48: Pass | E48: Pass with note: the spatial aggregation and median-Au ranking are reproduced correctly, but the SQL restricts samples to longitude 120.5–122.5 and latitude -32.0–-28.5 although the question does not state this geographic restriction. The ≥5,000 threshold is also evaluated after the assay join and valid-Au filtering. Rows with tied rounded median values may appear in different relative order. | F48: Clarify the geographic bounding box in the question if it is intentional; otherwise compare all map sheets. If “at least 5000 soil samples” refers to all soil samples regardless of Au availability, determine eligibility before filtering valid Au assays. Add a secondary map-sheet tie-breaker if deterministic ordering is required. | G48: NS3-042.csv | H48: Thomas_GeoQueryBench_New_Query_Error_Report(1).xlsx
A49: Thomas | B49: CD1-027 | D49: Pass | E49: Pass with note: For nearest drill holes with no intercept satisfying the 4 m minimum, 0.5 g/t cutoff and 2 m dilution criteria, the supplied result represents the absence of a qualifying intercept as best_grade_gpt = 0.00 and best_length_m = 0.00 rather than as a missing/not-found value. | F49: Consider representing cases with no qualifying significant intercept as NULL/NA or explicitly labelling them as "no qualifying intercept" to distinguish absence from an actual zero-grade intercept. | G49: CD1-027.csv | H49: Thomas_GeoQueryBench_New_Query_Error_Report(1).xlsx
A50: Thomas | B50: CD2-019 | D50: Pass | E50: Pass with note: The comparison represents each drill hole by the lithology code of its single longest logged interval. This is a reasonable operational definition, but the question does not explicitly define how multiple lithology intervals in a hole should be reduced to one lithology. The nearest-hole step also does not explicitly resolve equally-nearest-hole ties. | F50: Document the intended drill-hole lithology definition; if dominant lithology is intended, consider aggregating interval thickness by lith_code before selecting the representative lithology. A deterministic tie policy should also be used if equally-nearest holes occur. | G50: CD2-019.csv | H50: Thomas_GeoQueryBench_New_Query_Error_Report(1).xlsx
... A59: Thomas | B59: NS5-030 | D59: Pass | E59: Pass with note: The histogram and logarithmic x-axis are appropriate, but the gold code applies an unstated au_ppm < 100 cutoff, so values at or above 100 ppm are excluded from the displayed soil-gold distribution. | F59: Remove the <100 ppm cutoff if the complete positive soil Au distribution is intended, or explicitly state the <100 ppm restriction in the question. | G59: NS5-030.png | H59: Thomas_GeoQueryBench_New_Query_Error_Report(1).xlsx

Sheet All Query Reviews
A1: Reviewer | B1: Query ID | C1: Domain / Category | D1: Query Type | E1: Method | F1: Difficulty | G1: Question (EN) | H1: Expected Rows | I1: Reference / Supplied Result | J1: Verification Result | K1: Reference / Supplied Rows | L1: Verification Rows | M1: Row Count / Expected Rows Check | N1: Column / Schema Check | O1: Value / Result Match | P1: Duplicate Rows | Q1: Missing Cells | R1: Negative Numeric Cells | S1: Negative Values by Column | T1: Sentinel Check | U1: Executable / File Present | V1: Supplied Query Runs | W1: Unit Check | X1: CRS Check | Y1: Domain Check | Z1: Logic Check | AA1: Gold Valid | AB1: Output / Visualisation Match | AC1: Tables, Fields and Joins | AD1: Spatial / Domain Correctness | AE1: Data Quality Concern | AF1: Geological Expert Review | AG1: Overall / Review Outcome | AH1: Requires Client Clarification | AI1: Independent Rerun | AJ1: Rerun Comparison | AK1: Rerun Summary | AL1: Finding / Corrected Result | AM1: Evidence Test | AN1: Decisive Evidence / Reviewer Justification | AO1: Chinese Notes | AP1: Gold Runtime (s) | AQ1: Source Workbook
A2: Ziyue | B2: CD1-021 | C2: CD | E2: GeoPandas | F2: hard | G2: Count soil samples within 1 km of a drill hole, building sample points from the stored geometry column rather than the longitude/latitude fields. | H2: 1 | I2: CD1-021.csv | N2: Pass | O2: Yes | T2: N/A | U2: Yes | W2: Pass | X2: Pass | Y2: Pass | Z2: Pass | AA2: Yes | AB2: Pass | AD2: Pass | AE2: N/A | AF2: No | AG2: Pass | AM2: test_cd1_questions.py::test_cd1_021_counts_soil_points_within_one_kilometre_from_stored_geometry | AN2: An independent chunked KD-tree calculation parsed the stored GeoParquet geometry column, projected both datasets to EPSG:9473 and queried the nearest of 1,836,002 hole points without using longitude/latitude to construct soil points. It reproduced 5,407,653 soil samples and 2,717,170 unique soils within 1,000 m of a drill hole. Evidence: test_cd1_questions.py::test_cd1_021_counts_soil_points_within_one_kilometre_from_stored_geometry (PASS). | AO2: 使用存储 geometry、EPSG:9473 和分块 KD-tree 独立重算，5,407,653 个土壤样品中 2,717,170 个位于钻孔 1 km 内，与 Gold 一致。 | AQ2: Ziyue_GeoQueryBench_New_Query_Error_Report(1).xlsx
A3: Ziyue | B3: CD1-022 | C3: CD | E3: GeoPandas | F3: hard | G3: Rank the 1:250k map sheets by drilling intensity (holes per 1000 km2) and show the top 10 with both hole count and surface-sample count. | H3: 10 | I3: CD1-022.csv | N3: Pass | O3: No | T3: N/A | U3: Yes | W3: Pass | X3: Pass | Y3: Pass | Z3: Fail | AA3: No | AB3: Fail | AD3: Fail | AE3: Yes | AF3: No | AG3: Fail | AM3: test_cd1_questions.py::test_cd1_022_counts_unique_samples_within_each_sheet | AN3: Projected sheet areas, the top-ten density ranking and all unique hole counts reproduced. The sample spatial join contains a small overlap: counting unique UID within each sheet gives WIDGIEMOOLTHA 409,281, while Gold globally drops UID after joining all sheets and reports 409,277. The four samples are arbitrarily assigned away from WIDGIEMOOLTHA; the result depends on spatial-join ordering. This is separate from the Gold ranking, which is driven by hole density and remains correct. Evidence: density test PASS; test_cd1_questions.py::test_cd1_022_counts_unique_samples_within_each_sheet (XFAIL). | AO3: 图幅面积、钻孔数和排名正确，但 Gold 在所有图幅连接后全局去重 UID，导致重叠区域中 WIDGIEMOOLTHA 任意少计 4 个地表样品（409,277 而非 409,281）。 | AQ3: Ziyue_GeoQueryBench_New_Query_Error_Report(1).xlsx
A4: Ziyue | B4: CD1-030 | C4: CD | E4: SQL | F4: hard | G4: In SQL, rank the 1:250k map sheets by drilling density (holes per 1000 square kilometres) and return the top ten. | H4: 10 | I4: CD1-030.csv | N4: Pass | O4: Yes | T4: N/A | U4: Yes | W4: Pass | X4: Pass | Y4: Fail | Z4: Fail | AA4: No | AB4: Fail | AD4: Pass | AE4: Yes | AF4: No | AG4: Fail | AM4: test_cd1_questions.py::test_cd1_030_sql_version_uses_same_drilling_population_as_cd1_022 | AN4: The supplied CSV exactly reproduces when using A_subsurface collar rows: 604,294 collars and the stated top ten. However, metadata calls this the SQL version of CD1-022, whose GeoPandas Gold uses the statewide B_surface drillhole_maxgrade population of 1,836,002 holes. The populations produce materially different rankings and densities: CD1-030 starts WIDGIEMOOLTHA 8,818.8 and KALGOORLIE 8,687.9, whereas CD1-022 starts KALGOORLIE 10,891.7 and WIDGIEMOOLTHA 7,857.4. The source/scope change is not disclosed by the question. Evidence: current-result test PASS; test_cd1_questions.py::test_cd1_030_sql_version_uses_same_drilling_population_as_cd1_022 (XFAIL). | AO4: 当前 CSV 可复现，但作为 CD1-022 的 SQL 版却从 1,836,002 个全州 maxgrade 钻孔换成 604,294 个四区域 collar，排名和密度明显不同，题目未说明范围变化。 | AQ4: Ziyue_GeoQueryBench_New_Query_Error_Report(1).xlsx
A5: Ziyue | B5: CD1-032 | C5: CD | E5: SQL | F5: medium | G5: Using the per-hole maximum grade layer, how many drill holes reached at least 1 g/t gold? | H5: 1 | I5: CD1-032.csv | N5: Pass | O5: Yes | T5: N/A | U5: Yes | W5: Pass | X5: N/A | Y5: Pass | Z5: Pass | AA5: Yes | AB5: Pass | AD5: N/A | AE5: N/A | AF5: No | AG5: Pass | AM5: test_cd1_questions.py::test_cd1_032_counts_unique_per_hole_maximum_gold_rows | AN5: The per-hole maximum-grade layer contains 1,836,002 unique hole_ref rows, so count(*) has hole semantics. Independent filtering at au_ppm >= 1 reproduced 248,754 qualifying holes and CD1-032.csv. Evidence: test_cd1_questions.py::test_cd1_032_counts_unique_per_hole_maximum_gold_rows (PASS). | AO5: 每孔最高品位层的 hole_ref 唯一；独立筛选 au_ppm >= 1 得到 248,754 个钻孔，与 Gold 一致。 | AQ5: Ziyue_GeoQueryBench_New_Query_Error_Report(1).xlsx
A6: Ziyue | B6: CD1-041 | C6: CD | E6: SQL | F6: medium | G6: How close is the nearest drill hole to each mineral occurrence in the Kalgoorlie box? Give the median and the ten most isolated occurrences. | H6: 10 | I6: CD1-041.csv | N6: Fail | O6: Yes | T6: N/A | U6: Yes | W6: Pass | X6: Pass | Y6: Pass | Z6: Pass | AA6: No | AB6: Fail | AD6: Pass | AE6: N/A | AF6: No | AG6: Fail | AM6: test_cd1_questions.py::test_cd1_041_output_includes_requested_median | AN6: Independent EPSG:7851 nearest-neighbour distances for 265 mineral occurrences reproduced all ten isolated sites in CD1-041.csv. The median nearest-hole distance is 61.624 m, but neither the Gold SQL nor CSV returns it even though the question explicitly requests the median. Grouping by site_title can also collapse repeated titles. Evidence: top-ten test PASS; test_cd1_questions.py::test_cd1_041_output_includes_requested_median (XFAIL). | AO6: 最孤立的 10 个矿点可复现，但题目要求的最近钻孔距离中位数 61.624 m 在 Gold SQL 和 CSV 中完全缺失。 | AQ6: Ziyue_GeoQueryBench_New_Query_Error_Report(1).xlsx
A7: Ziyue | B7: CD1-042 | C7: CD | E7: SQL | F7: easy | G7: How many hydrogeochemistry (groundwater) sites are there, and how many of them sit inside a region that has drilling? | H7: 2 | I7: CD1-042.csv | N7: Pass | O7: Yes | T7: N/A | U7: Yes | W7: Pass | X7: Pass | Y7: Pass | Z7: Pass | AA7: Yes | AB7: Pass | AD7: Pass | AE7: N/A | AF7: No | AG7: Pass | AM7: test_cd1_questions.py::test_cd1_042_counts_groundwater_sites_inside_four_drilled_regions | AN7: Independent geometry-coordinate membership checks reproduced 40,581 groundwater sites in total and 973 strictly inside the union of the four drilled-region boxes. Schema and bucket labels matched CD1-042.csv. Evidence: test_cd1_questions.py::test_cd1_042_counts_groundwater_sites_inside_four_drilled_regions (PASS). | AO7: 独立空间判断得到地下水点总数 40,581，其中 973 个严格位于四个钻探区域框内，与 Gold 一致。 | AQ7: Ziyue_GeoQueryBench_New_Query_Error_Report(1).xlsx
A8: Ziyue | B8: CD1-045 | C8: CD | E8: Visualisation | F8: easy | G8: Draw a map of the Kambalda box showing surface samples and drill collars as two layers. | H8: 1 | I8: CD1-045.png | N8: N/A | O8: Yes | T8: N/A | U8: Yes | W8: Pass | X8: Pass with caveat | Y8: Pass | Z8: Pass | AA8: Yes | AB8: Pass | AD8: Pass | AE8: N/A | AF8: No | AG8: Pass with note | AM8: test_cd1_questions.py::test_cd1_045_reconstructs_two_layer_kambalda_map_contract | AN8: The reconstructed Kambalda selection contained 14,841 surface samples and 28,421 drill collars. Two distinct layers, count-bearing legend entries, labels, title and equal coordinate aspect rendered successfully; the supplied 966x655 PNG is readable and nonblank. Equal aspect in geographic degrees is only an approximation of physical scale, but it is adequate for the requested qualitative overlay. Evidence: test_cd1_questions.py::test_cd1_045_reconstructs_two_layer_kambalda_map_contract (PASS). | AO8: Kambalda 框内 14,841 个地表样品和 28,421 个孔口，两层、图例和非空 PNG 均通过；经纬度 equal aspect 仅是近似比例。 | AQ8: Ziyue_GeoQueryBench_New_Query_Error_Report(1).xlsx
A9: Ziyue | B9: CD1-054 | C9: CD | E9: Visualisation | F9: hard | G9: Draw a proportional symbol map of drilling intensity per 5 km cell in the Kalgoorlie box, with symbol area scaled to hole count. | H9: 1 | I9: CD1-054.png | N9: N/A | O9: Yes | T9: N/A | U9: Yes | W9: Pass | X9: Pass | Y9: Pass | Z9: Pass | AA9: Yes | AB9: Pass | AD9: Pass | AE9: N/A | AF9: No | AG9: Pass | AM9: test_cd1_questions.py::test_cd1_054_uses_symbol_area_proportional_to_five_km_cell_count | AN9: Independent reconstruction projected all 373,776 R1 collars to EPSG:7851, produced 511 five-kilometre cells and confirmed symbol area s is linearly proportional to hole count. The three reference legend counts are 284, 1,734 and 10,225 holes; equal aspect and the readable nonblank Gold PNG passed. Evidence: test_cd1_questions.py::test_cd1_054_uses_symbol_area_proportional_to_five_km_cell_count (PASS). | AO9: 373,776 个 R1 钻孔形成 511 个 5 km 网格；符号面积与孔数线性成正比，分级图例与 PNG 均通过。 | AQ9: Ziyue_GeoQueryBench_New_Query_Error_Report(1).xlsx
A10: Ziyue | B10: CD2-020 | C10: CD | E10: Python | F10: hard | G10: Compare sulfur levels between surface and subsurface data. Careful: the two databases store sulfur in different units. | H10: 2 | I10: CD2-020.csv | N10: Pass | O10: Yes | T10: Pass | U10: Yes | W10: Pass | X10: N/A | Y10: Pass | Z10: Pass | AA10: Yes | AB10: Pass | AD10: N/A | AE10: N/A | AF10: No | AG10: Pass | AM10: test_cd2_questions.py::test_cd2_020_recomputes_sulfur_in_common_ppm_units | AN10: Independent DuckDB recomputation retained non-negative sulfur values as documented, converted surface s_pct to ppm using 1 pct = 10,000 ppm, and reproduced both Gold rows. Surface: n=1,007,378, median=238.0 ppm, p95=2,523.5 ppm. Subsurface: n=2,016,020, median=500.0 ppm, p95=109,900.0 ppm. Schema, row count, units, sentinel handling and values matched CD2-020.csv. Evidence: test_cd2_questions.py::test_cd2_020_recomputes_sulfur_in_common_ppm_units (PASS). | AO10: 独立重算与 Gold 完全一致；正确保留零值、排除负哨兵，并将地表硫从百分比换算为 ppm。 | AQ10: Ziyue_GeoQueryBench_New_Query_Error_Report(1).xlsx
A11: Ziyue | B11: CD2-023 | C11: CD | E11: SQL | F11: hard | G11: Report-level footprint: for the ten WAMEX reports that contributed the most surface samples, how many drill holes does each also contribute? | H11: 10 | I11: CD2-023.csv | N11: Pass | O11: Yes | T11: N/A | U11: Yes | W11: Pass | X11: N/A | Y11: Pass | Z11: Pass | AA11: Yes | AB11: Pass | AD11: N/A | AE11: Yes | AF11: No | AG11: Pass with note | AM11: test_cd2_questions.py::test_cd2_023_preserves_top_surface_reports_without_drill_holes | AN11: Independent aggregation reproduced the ten largest surface-sample WAMEX reports and verified that the tenth count exceeds the eleventh, so the LIMIT 10 boundary is unambiguous. A left merge with collar counts preserved all ten reports; nine have zero drill holes and report 98358 has 181. Collar row counts equalled distinct hole_id counts. Schema, identifiers, ordering and values matched CD2-023.csv. The nine zero drill-hole counts are valid outputs but remain a cross-dataset coverage or lineage concern. Evidence: test_cd2_questions.py::test_cd2_023_preserves_top_surface_reports_without_drill_holes (PASS). | AO11: 结果匹配；LEFT JOIN 正确保留 9 个无钻孔记录的高地表采样报告，但这仍是跨数据集覆盖或谱系问题。 | AQ11: Ziyue_GeoQueryBench_New_Query_Error_Report(1).xlsx
A12: Ziyue | B12: CD2-024 | C12: CD | E12: GeoPandas | F12: hard | G12: Are nickel anomalies consistent across scales? Within the Kambalda box (lon 121.5-121.8, lat -31.3 to -31.1), compare the share of soil samples above 500 ppm Ni against the share of holes whose maximum downhole Ni exceeds 5000 ppm. | H12: 1 | I12: CD2-024.csv | N12: Pass | O12: Yes | T12: Pass | U12: Yes | W12: Pass | X12: Pass | Y12: Pass | Z12: Pass | AA12: Yes | AB12: Pass | AD12: Pass | AE12: N/A | AF12: Yes | AG12: Pass with note | AM12: test_cd2_questions.py::test_cd2_024_recomputes_kambalda_nickel_proportions | AN12: Independent recomputation used the inclusive Kambalda box, soil-only surface samples, non-negative Ni values and strict anomaly thresholds. It reproduced 5,895 measured soil samples with 10.04% over 500 ppm and 7,426 measured drill holes with 36.37% over 5,000 ppm. Surface UIDs and hole references were unique, and the GeoParquet CRS was EPSG:7844. The Gold comparison is numerically valid, but the two percentages use different media, thresholds and denominators; deciding whether they are geologically consistent requires domain judgement. Evidence: test_cd2_questions.py::test_cd2_024_recomputes_kambalda_nickel_proportions (PASS). | AO12: 结果匹配且空间、CRS、阈值均正确；但两侧介质、阈值和分母不同，不能仅凭两个百分比直接判定地质上一致。 | AQ12: Ziyue_GeoQueryBench_New_Query_Error_Report(1).xlsx
A13: Ziyue | B13: CD2-035 | C13: CD | E13: SQL | F13: medium | G13: For each region, compare how many surface samples and how many drill holes fall inside it, and give the ratio. | H13: 4 | I13: CD2-035.csv | N13: Pass | O13: Yes | T13: N/A | U13: Yes | W13: Pass | X13: N/A | Y13: Pass | Z13: Pass | AA13: Yes | AB13: Pass | AD13: Pass | AE13: N/A | AF13: No | AG13: Pass | AM13: test_cd2_questions.py::test_cd2_035_recomputes_surface_per_hole_by_region | AN13: Independent bounding-box counts reproduced all four region rows and verified that collar row counts equal distinct hole_id counts. The reported surface-per-hole direction and rounded ratios matched CD2-035.csv: R4 64,514/37,198=1.73; R2 208,366/135,888=1.53; R1 534,994/373,776=1.43; R3 1,302/57,432=0.02. Evidence: test_cd2_questions.py::test_cd2_035_recomputes_surface_per_hole_by_region (PASS). | AO13: 四个区域的地表样品数、唯一钻孔数及 surface/hole 比值均与 Gold 一致。 | AQ13: Ziyue_GeoQueryBench_New_Query_Error_Report(1).xlsx
... A33: Ziyue | B33: NS1-021 | C33: NS | E33: SQL | F33: medium | G33: Using the GSWA WACHEM quality-controlled dataset, list samples with gold above 100 ppb, showing sample ID, lithology and the gold value. | H33: 202 | I33: NS1-021.csv | N33: Pass | O33: Yes | T33: N/A | U33: Yes | W33: Pass | X33: N/A | Y33: Pass | Z33: Pass | AA33: Yes | AB33: Pass | AD33: N/A | AE33: Yes | AF33: No | AG33: Pass with note | AM33: test_ns1_questions.py::test_ns1_021_recomputes_wachem_gold_above_100_ppb | AN33: Independent WACHEM filtering reproduced all 202 rows above 0.1 ppm Au and their values. There are only 200 unique sample IDs because two IDs appear twice with different analytical values; the row-level answer is valid, but consumers should not interpret 202 rows as 202 unique samples. Evidence: test_ns1_questions.py::test_ns1_021_recomputes_wachem_gold_above_100_ppb (PASS). | AO33: 202 条高于 100 ppb 的记录可复现，但只有 200 个唯一 sample_id；两组同 ID 不同值需作数据质量说明。 | AQ33: Ziyue_GeoQueryBench_New_Query_Error_Report(1).xlsx
A34: Ziyue | B34: NS1-029 | C34: NS | E34: SQL | F34: medium | G34: Which laboratory analysed each of the surface samples, and by what method? | I34: NS1-029.txt | N34: N/A | O34: Yes | T34: N/A | U34: Yes | W34: N/A | X34: N/A | Y34: Pass | Z34: Pass | AA34: Yes | AB34: Pass | AD34: N/A | AE34: Yes | AF34: Yes | AG34: Pass | AM34: test_ns1_questions.py::test_ns1_029_correctly_refuses_unavailable_lab_and_method_fields | AN34: Schema inspection confirms that surface_sample and surface_assay contain no laboratory, method, batch or detection-limit fields. The supplied text correctly refuses to invent an answer and explains the resulting comparability limitation. Evidence: test_ns1_questions.py::test_ns1_029_correctly_refuses_unavailable_lab_and_method_fields (PASS). | AO34: 地表样品与化验表确实没有实验室、方法、批次或检出限字段；Gold 正确拒答，没有臆造信息。 | AQ34: Ziyue_GeoQueryBench_New_Query_Error_Report(1).xlsx
A35: Ziyue | B35: NS1-032 | C35: NS | E35: SQL | F35: easy | G35: List the soil samples that returned a bismuth value. | I35: NS1-032.csv | N35: Pass | O35: Yes | T35: Pass | U35: Yes | W35: Pass | X35: N/A | Y35: Pass | Z35: Pass | AA35: Yes | AB35: Pass | AD35: N/A | AE35: Yes | AF35: No | AG35: Pass with note | AM35: test_ns1_questions.py::test_ns1_032_empty_soil_bismuth_result_is_supported_by_data | AN35: All 5,407,653 soil rows have bi_ppm at the -9999 sentinel maximum, so no positive measured bismuth value exists. The empty CSV has the requested sample_id and bi_ppm schema and is correct, while also exposing complete absence of usable soil Bi data. Evidence: test_ns1_questions.py::test_ns1_032_empty_soil_bismuth_result_is_supported_by_data (PASS). | AO35: 5,407,653 个土壤样品的 Bi 最大值仍为 -9999 哨兵，因此空结果正确，但也说明该字段完全没有可用数据。 | AQ35: Ziyue_GeoQueryBench_New_Query_Error_Report(1).xlsx
A36: Ziyue | B36: NS1-037 | C36: NS | E36: GeoPandas | F36: medium | G36: Which named geological units have the most surface samples in them? Give the top fifteen with unit name and rock type. | H36: 15 | I36: NS1-037.csv | N36: Pass | O36: Yes | T36: N/A | U36: Yes | W36: Pass | X36: Pass | Y36: Fail | Z36: Fail | AA36: No | AB36: Fail | AD36: Fail | AE36: Yes | AF36: No | AG36: Fail | AM36: test_ns1_questions.py::test_ns1_037_question_discloses_gold_geographic_scope | AN36: The supplied CSV contains 15 sorted rows under the implemented calculation, but Gold silently restricts samples and geology to longitude 120.5-122.5 and latitude -32 to -28.5. The question asks which named units have the most samples without naming that region, so the statewide ranking is not answered. Evidence: shape test PASS; test_ns1_questions.py::test_ns1_037_question_discloses_gold_geographic_scope (XFAIL). | AO36: Gold 使用题目未说明的经纬度框，只回答局部地区而非全州具名地质单元排名，Gold Valid=No。 | AQ36: Ziyue_GeoQueryBench_New_Query_Error_Report(1).xlsx
A37: Ziyue | B37: NS1-043 | C37: NS | E37: SQL | F37: medium | G37: What is the pH of groundwater in this dataset? | H37: 2 | I37: NS1-043.csv | N37: Pass | O37: Yes | T37: N/A | U37: Yes | W37: Pass | X37: N/A | Y37: Pass | Z37: Pass | AA37: Yes | AB37: Pass | AD37: N/A | AE37: N/A | AF37: No | AG37: Pass | AM37: test_ns1_questions.py::test_ns1_043_recomputes_laboratory_and_field_groundwater_ph | AN37: Independent valid-range filtering reproduced both pH definitions: laboratory n=35,441, mean 6.98, median 7.2; field n=1,774, mean 6.59, median 6.8. Separating the two columns avoids presenting one ambiguous pH value. Evidence: test_ns1_questions.py::test_ns1_043_recomputes_laboratory_and_field_groundwater_ph (PASS). | AO37: 实验室与现场 pH 的有效数量、均值和中位数均可复现；分别报告两种定义是正确做法。 | AQ37: Ziyue_GeoQueryBench_New_Query_Error_Report(1).xlsx
A38: Ziyue | B38: NS1-049 | C38: NS | E38: SQL | F38: easy | G38: How many groundwater analyses are there, and how many have a complete major-ion set? | H38: 1 | I38: NS1-049.csv | N38: Pass | O38: Yes | T38: N/A | U38: Yes | W38: Pass | X38: N/A | Y38: Fail | Z38: Fail | AA38: No | AB38: Fail | AD38: N/A | AE38: Yes | AF38: Yes | AG38: Fail | AM38: test_ns1_questions.py::test_ns1_049_complete_major_ions_include_potassium | AN38: Gold correctly reports 40,581 analyses, 35,441 valid laboratory pH values and 36,478 positive TDS values. Its complete-major-ion test returns 23,314 rows but omits potassium even though k_mgl is present; including Na, K, Ca, Mg, Cl, SO4 and HCO3 gives 23,269 complete rows. Evidence: current-definition test PASS; test_ns1_questions.py::test_ns1_049_complete_major_ions_include_potassium (XFAIL). | AO38: 总数、pH 和 TDS 正确，但“主要离子齐全”漏掉 K；包含钾后应为 23,269，而非 23,314。 | AQ38: Ziyue_GeoQueryBench_New_Query_Error_Report(1).xlsx
A39: Ziyue | B39: NS1-051 | C39: NS | E39: Visualisation | F39: medium | G39: Draw a 100 percent stacked bar of sample medium composition per map sheet, for the ten sheets with the most samples. | H39: 1 | I39: NS1-051.png | N39: N/A | O39: No | T39: N/A | U39: Yes | W39: Pass | X39: Pass | Y39: Fail | Z39: Fail | AA39: No | AB39: Fail | AD39: Pass | AE39: Yes | AF39: No | AG39: Fail | AM39: test_ns1_questions.py::test_ns1_051_delivered_chart_contains_plot_data | AN39: The PNG file is readable, but pixel inspection and visual review confirm that it contains only title, empty axes and an empty legend marker: there are no coloured stacked bars or map-sheet labels. Gold also filters samples to an undisclosed regional bbox before choosing the top sheets, while the question asks for the ten sheets with most samples generally. Evidence: empty-image check PASS; test_ns1_questions.py::test_ns1_051_delivered_chart_contains_plot_data (XFAIL). | AO39: 交付 PNG 可打开但只有标题、空坐标轴和空图例，没有任何堆叠条或图幅名称；代码还使用未披露范围框，Gold Valid=No。 | AQ39: Ziyue_GeoQueryBench_New_Query_Error_Report(1).xlsx
A40: Ziyue | B40: NS2-018 | C40: NS | E40: SQL | F40: hard | G40: How many groundwater analyses were sampled each year, and what was that year's median TDS? | H40: 5 | I40: NS2-018.csv | N40: Pass | O40: Yes | T40: N/A | U40: Yes | W40: Pass | X40: N/A | Y40: Pass | Z40: Pass | AA40: Yes | AB40: Pass | AD40: N/A | AE40: Yes | AF40: No | AG40: Pass with note | AM40: test_ns2_questions.py::test_ns2_018_recomputes_yearly_groundwater_counts_and_tds_medians | AN40: Independent date grouping reproduced all five yearly rows: 2002 52/617, 2003 255/592, 2004 325/689, 2005 312/812 and 2006 21/707. Only 965 of 40,581 groundwater rows have a sample_date, so the result is correct for dated analyses but has severe temporal coverage limitations. Evidence: test_ns2_questions.py::test_ns2_018_recomputes_yearly_groundwater_counts_and_tds_medians (PASS). | AO40: 五个年份的数量和 TDS 中位数均可复现；但 40,581 条中仅 965 条有日期，需注明时间覆盖极低。 | AQ40: Ziyue_GeoQueryBench_New_Query_Error_Report(1).xlsx
A41: Ziyue | B41: NS2-023 | C41: NS | E41: SQL | F41: medium | G41: What is the most frequently observed mineral in WAROX field observations, and how many times more common is it than the second most frequent? | H41: 1 | I41: NS2-023.csv | N41: Pass | O41: Yes | T41: N/A | U41: Yes | W41: Pass | X41: N/A | Y41: Pass | Z41: Pass | AA41: Yes | AB41: Pass | AD41: N/A | AE41: N/A | AF41: No | AG41: Pass | AM41: test_ns2_questions.py::test_ns2_023_recomputes_two_most_frequent_warox_minerals | AN41: Independent WAROX mineral-category counts identify Quartz at 50,308 and Biotite at 20,435, giving the reported 2.46 ratio. Schema and values match NS2-023.csv. Evidence: test_ns2_questions.py::test_ns2_023_recomputes_two_most_frequent_warox_minerals (PASS). | AO41: WAROX 矿物观测中 Quartz 50,308、Biotite 20,435，倍数 2.46，与 Gold 一致。 | AQ41: Ziyue_GeoQueryBench_New_Query_Error_Report(1).xlsx
A42: Ziyue | B42: NS2-027 | C42: NS | E42: SQL | F42: hard | G42: Which soil samples came back unusually high in gold? Treat the top 5 percent of measured values as unusual. | H42: 183412 | I42: NS2-027.csv | N42: Pass | O42: Yes | T42: Pass | U42: Yes | W42: Pass | X42: N/A | Y42: Pass | Z42: Pass | AA42: Yes | AB42: Pass | AD42: N/A | AE42: Yes | AF42: No | AG42: Pass with note | AM42: test_ns2_questions.py::test_ns2_027_recomputes_strict_top_five_percent_soil_gold_rule | AN42: Independent soil/assay joining produced 3,674,753 non-negative measured Au values, a continuous 95th percentile of 0.068 ppm and 183,412 rows strictly above it, matching Gold's row count and maximum 537,099.97 ppm. The extreme maximum and many very high values warrant source/unit review, but the stated percentile rule is correctly applied. Evidence: test_ns2_questions.py::test_ns2_027_recomputes_strict_top_five_percent_soil_gold_rule (PASS). | AO42: 3,674,753 个可用值、P95=0.068 ppm、严格大于阈值的 183,412 条均正确；极端最大值 537,099.97 ppm 需作数据质量说明。 | AQ42: Ziyue_GeoQueryBench_New_Query_Error_Report(1).xlsx
A43: Ziyue | B43: NS2-038 | C43: NS | E43: GeoPandas | F43: easy | G43: What proportion of groundwater analyses have a usable pH, and what is the real range? | H43: 1 | I43: NS2-038.csv | N43: Pass | O43: Yes | T43: Pass | U43: Yes | W43: Pass | X43: N/A | Y43: Pass | Z43: Pass | AA43: Yes | AB43: Pass | AD43: N/A | AE43: N/A | AF43: No | AG43: Pass | AM43: test_ns2_questions.py::test_ns2_038_recomputes_usable_groundwater_ph_proportion_and_range | AN43: Independent valid-range filtering reproduced 40,581 rows, 35,441 usable pH values, 87.3% valid of non-null, valid mean 6.98 and range 1.8-10.94. The naive -1260.4 mean correctly demonstrates sentinel contamination. Evidence: test_ns2_questions.py::test_ns2_038_recomputes_usable_groundwater_ph_proportion_and_range (PASS). | AO43: 有效 pH 数量、87.3% 比例、均值及 1.8–10.94 范围均可复现；原始均值显示哨兵污染。 | AQ43: Ziyue_GeoQueryBench_New_Query_Error_Report(1).xlsx
A44: Ziyue | B44: NS2-041 | C44: NS | E44: SQL | F44: medium | G44: In the WA geochemistry table, what is the typical major-oxide composition? Give median Al2O3 and CaO by sample type. | H44: 4 | I44: NS2-041.csv | N44: Pass | O44: Yes | T44: N/A | U44: Yes | W44: Pass | X44: N/A | Y44: Pass | Z44: Pass | AA44: Yes | AB44: Pass | AD44: N/A | AE44: Yes | AF44: No | AG44: Pass with note | AM44: test_ns2_questions.py::test_ns2_041_recomputes_major_oxide_medians_by_sample_type | AN44: Independent grouping reproduced the four sample-type row counts and positive-value Al2O3/CaO medians. The n column is the total group row count, not the count with both oxide values usable; this is a clarity/data-coverage note, not a numerical mismatch. Evidence: test_ns2_questions.py::test_ns2_041_recomputes_major_oxide_medians_by_sample_type (PASS). | AO44: 四类样品的行数和两种正值中位数正确；n 是组内总行数，不是两种氧化物同时可用的数量，需说明。 | AQ44: Ziyue_GeoQueryBench_New_Query_Error_Report(1).xlsx
A45: Ziyue | B45: NS2-048 | C45: NS | E45: GeoPandas | F45: easy | G45: How many surface samples and what median gold does each greenstone belt have? | H45: 12 | I45: NS2-048.csv | N45: Pass | O45: Yes | T45: Pass with caveat | U45: Yes | W45: Pass | X45: Pass | Y45: Fail | Z45: Fail | AA45: No | AB45: Fail | AD45: Pass | AE45: Yes | AF45: Yes | AG45: Fail | AM45: test_ns2_questions.py::test_ns2_048_answers_each_greenstone_belt_without_hidden_medium_or_top_n_filters | AN45: Gold's filtered computation is reproducible: 20 belt groups are present, 18 meet n>=200, and the CSV contains the top 12 by median after restricting to soil and 0<Au<100. The question asks how many surface samples and median gold each belt has; it does not authorize soil-only selection, excluding non-positive/high values, n>=200 or top-12 truncation. Evidence: filtered reproduction PASS; test_ns2_questions.py::test_ns2_048_answers_each_greenstone_belt_without_hidden_medium_or_top_n_filters (XFAIL). | AO45: Gold 的筛选后前 12 可复现，但题目要求每条绿岩带的地表样品；土壤限定、Au 范围、n>=200 和 top12 均未说明，Gold Valid=No。 | AQ45: Ziyue_GeoQueryBench_New_Query_Error_Report(1).xlsx
A46: Ziyue | B46: NS3-017 | C46: NS | E46: GeoPandas | F46: medium | G46: How many surface samples of each medium fall inside the Hamersley Basin? | H46: 4 | I46: NS3-017.csv | N46: Pass | O46: Yes | T46: N/A | U46: Yes | W46: Pass | X46: Pass | Y46: Pass | Z46: Pass | AA46: Yes | AB46: Pass | AD46: Pass | AE46: N/A | AF46: No | AG46: Pass | AM46: test_ns3_questions.py::test_ns3_017_recomputes_sample_media_inside_hamersley_basin | AN46: Independent point-in-polygon membership and UID de-duplication reproduced all Hamersley Basin medium counts: rock_chip 9,911, shallow_drill 4, soil 7,232 and stream_sed 1,382. Evidence: test_ns3_questions.py::test_ns3_017_recomputes_sample_media_inside_hamersley_basin (PASS). | AO46: Hamersley Basin 内四类介质数量均经独立空间连接复现，与 Gold 一致。 | AQ46: Ziyue_GeoQueryBench_New_Query_Error_Report(1).xlsx
A47: Ziyue | B47: NS3-018 | C47: NS | E47: GeoPandas | F47: hard | G47: Duplicate detection: within the Kalgoorlie box (lon 121.2-121.8, lat -31.0 to -30.5), how many pairs of soil samples sit within 10 m of each other but carry different sample IDs? | H47: 1 | I47: NS3-018.csv | N47: Pass | O47: Yes | T47: N/A | U47: Yes | W47: Pass | X47: Pass | Y47: Pass | Z47: Fail | AA47: No | AB47: Fail | AD47: Pass | AE47: Yes | AF47: No | AG47: Fail | AM47: test_ns3_questions.py::test_ns3_018_gold_matches_exact_dwithin_pair_count | AN47: An exact projected cKDTree query found 43,884 unordered soil-sample pairs at distance <=10 m, all with different sample IDs; 36,199 pairs have zero coordinate distance. Gold's polygon-buffer/within approximation reports 43,882 and misses two boundary pairs. Evidence: exact-count test PASS; test_ns3_questions.py::test_ns3_018_gold_matches_exact_dwithin_pair_count (XFAIL). | AO47: 精确 <=10 m 最近对为 43,884（全部 ID 不同），Gold 的 buffer/within 近似漏掉边界上的 2 对，Gold Valid=No。 | AQ47: Ziyue_GeoQueryBench_New_Query_Error_Report(1).xlsx
A48: Ziyue | B48: NS3-028 | C48: NS | E48: SQL | F48: medium | G48: Which stream sediment samples returned gold above 1000 ppm? | I48: NS3-028.csv | N48: Pass | O48: Yes | T48: Pass | U48: Yes | W48: Pass | X48: N/A | Y48: Pass | Z48: Pass | AA48: Yes | AB48: Pass | AD48: N/A | AE48: Yes | AF48: No | AG48: Pass with note | AM48: test_ns3_questions.py::test_ns3_028_empty_stream_sediment_result_is_supported_by_maximum | AN48: Independent joining shows the maximum stream-sediment Au is 967 ppm, below the strict >1,000 ppm threshold. The empty CSV and requested schema are therefore correct; the unusually high maximum remains a data-quality/unit-review note. Evidence: test_ns3_questions.py::test_ns3_028_empty_stream_sediment_result_is_supported_by_maximum (PASS). | AO48: 河流沉积物 Au 最大值为 967 ppm，未超过严格阈值 1,000，因此空结果正确；极高数值仍需数据质量复核。 | AQ48: Ziyue_GeoQueryBench_New_Query_Error_Report(1).xlsx
A49: Ziyue | B49: NS3-029 | C49: NS | E49: GeoPandas | F49: hard | G49: What is the gold content around Kalgoorlie? | H49: 3 | I49: NS3-029.csv | N49: Pass | O49: Yes | T49: Pass | U49: Yes | W49: Pass | X49: Pass | Y49: Pass | Z49: Pass | AA49: Yes | AB49: Pass | AD49: Pass | AE49: Yes | AF49: Yes | AG49: Pass with note | AM49: test_ns3_questions.py::test_ns3_029_recomputes_three_disclosed_kalgoorlie_distance_summaries | AN49: Gold explicitly exposes assumptions for an underspecified question: soil, surface assays, city-centre coordinate, three radii and three statistics. Independent projection and distance calculations reproduced 5 km n=0; 10 km n=1,307, mean 0.0188, median 0.014, p95 0.044; and 25 km n=34,467, mean 18.5071, median 0.009, p95 0.042. The extreme 25 km mean is dominated by outliers and should not be treated as typical. Evidence: test_ns3_questions.py::test_ns3_029_recomputes_three_disclosed_kalgoorlie_distance_summaries (PASS). | AO49: Gold 明确披露欠指定题目的假设，三种半径统计均可复现；25 km 均值被极端值强烈拉高，需结合中位数与 P95 解读。 | AQ49: Ziyue_GeoQueryBench_New_Query_Error_Report(1).xlsx
A50: Ziyue | B50: NS3-033 | C50: NS | E50: GeoPandas | F50: medium | G50: How far are surface samples from the nearest mapped fault, and does gold vary with that distance? | H50: 6 | I50: NS3-033.csv | N50: Pass | O50: Yes | T50: Pass with caveat | U50: Yes | W50: Pass | X50: Pass | Y50: Fail | Z50: Fail | AA50: No | AB50: Fail | AD50: Fail | AE50: Yes | AF50: No | AG50: Fail | AM50: test_ns3_questions.py::test_ns3_033_question_discloses_gold_scope_and_filters | AN50: The six-band CSV is internally ordered and contains 66,899 joined rows, but Gold silently restricts both samples and faults to a Kalgoorlie bbox, selects soil only and excludes Au <=0 or >=100. The general question discloses none of those filters. A tied nearest-fault join can also duplicate a sample row. Evidence: package test PASS; test_ns3_questions.py::test_ns3_033_question_discloses_gold_scope_and_filters (XFAIL). | AO50: Gold 使用未说明的 Kalgoorlie 范围、土壤介质和 Au 范围，并可能因最近断层并列重复样品，未回答通用题意。 | AQ50: Ziyue_GeoQueryBench_New_Query_Error_Report(1).xlsx
A51: Ziyue | B51: NS3-035 | C51: NS | E51: GeoPandas | F51: medium | G51: How dense is the surface sampling in each region box? Give samples per square kilometre. | H51: 4 | I51: NS3-035.csv | N51: Pass | O51: Yes | T51: N/A | U51: Yes | W51: Pass | X51: Pass | Y51: Pass | Z51: Pass | AA51: Yes | AB51: Pass | AD51: Pass | AE51: N/A | AF51: No | AG51: Pass | AM51: test_ns3_questions.py::test_ns3_035_recomputes_sampling_density_for_four_region_boxes | AN51: Independent bbox counts and EPSG:9473 polygon areas reproduced all four rows: R1 534,994/15,841=33.77, R2 208,366/8,090=25.76, R4 64,514/10,247=6.30 and R3 1,302/6,404=0.20 samples per square kilometre. Evidence: test_ns3_questions.py::test_ns3_035_recomputes_sampling_density_for_four_region_boxes (PASS). | AO51: 四个区域框的样品数、投影面积和每平方公里密度均可复现。 | AQ51: Ziyue_GeoQueryBench_New_Query_Error_Report(1).xlsx
A52: Ziyue | B52: NS3-039 | C52: NS | E52: SQL | F52: easy | G52: List the soil samples that have a chromium value. | I52: NS3-039.csv | N52: Pass | O52: Yes | T52: Pass | U52: Yes | W52: Pass | X52: N/A | Y52: Pass | Z52: Pass | AA52: Yes | AB52: Pass | AD52: N/A | AE52: Yes | AF52: No | AG52: Pass with note | AM52: test_ns3_questions.py::test_ns3_039_empty_soil_chromium_result_is_supported_by_data | AN52: All joined soil chromium values remain at the -9999 sentinel maximum, so there is no positive measured Cr value. The empty result is correct but records a complete data-availability gap for soil chromium. Evidence: test_ns3_questions.py::test_ns3_039_empty_soil_chromium_result_is_supported_by_data (PASS). | AO52: 土壤 Cr 最大值仍是 -9999 哨兵，空结果正确；同时说明土壤铬字段没有可用测值。 | AQ52: Ziyue_GeoQueryBench_New_Query_Error_Report(1).xlsx
A53: Ziyue | B53: NS3-047 | C53: NS | E53: SQL | F53: medium | G53: Which townsites have the most surface samples within 10 km? | H53: 6 | I53: NS3-047.csv | N53: Pass | O53: Yes | T53: N/A | U53: Yes | W53: Pass | X53: Pass | Y53: Fail | Z53: Fail | AA53: No | AB53: Fail | AD53: Fail | AE53: Yes | AF53: No | AG53: Fail | AM53: test_ns3_questions.py::test_ns3_047_question_discloses_gold_sample_bbox | AN53: Gold returns six towns sorted by nearby sample count, but the SQL first limits samples to longitude 120.5-122.5 and latitude -32 to -28.5. The question asks which townsites have the most samples within 10 km without defining that regional restriction, so statewide candidates are omitted and even the requested top ten cannot be produced. Evidence: shape test PASS; test_ns3_questions.py::test_ns3_047_question_discloses_gold_sample_bbox (XFAIL). | AO53: Gold 用未披露范围框筛样品，只返回 6 个城镇，无法代表全州 10 km 内样品最多的前十，Gold Valid=No。 | AQ53: Ziyue_GeoQueryBench_New_Query_Error_Report(1).xlsx
A54: Ziyue | B54: NS4-021 | C54: NS | E54: GeoPandas | F54: hard | G54: Rank As, Sb, Bi, W, Cu and Ag by their correlation with gold in rock chips, showing rank, correlation and the number of usable pairs. | H54: 6 | I54: NS4-021.csv | N54: Pass | O54: Yes | T54: N/A | U54: Yes | W54: Pass | X54: N/A | Y54: Pass | Z54: Pass | AA54: Yes | AB54: Pass | AD54: N/A | AE54: Yes | AF54: Yes | AG54: Pass with note | AM54: test_ns4_questions.py::test_ns4_021_recomputes_rock_chip_element_correlations_with_gold | AN54: Independent rock-chip joining and pairwise non-negative filtering reproduced all six usable-pair counts, correlations and ranks. Every rounded correlation is near zero (0.0000 to -0.0004), so the numerical ranking is valid but should not be interpreted as meaningful geological association without robust/outlier-aware analysis. Evidence: test_ns4_questions.py::test_ns4_021_recomputes_rock_chip_element_correlations_with_gold (PASS). | AO54: 六种元素的可用对数、相关系数和排名均可复现；相关性几乎为零，排名数值正确但不代表有实质地质关系。 | AQ54: Ziyue_GeoQueryBench_New_Query_Error_Report(1).xlsx
A55: Ziyue | B55: NS4-023 | C55: NS | E55: SQL | F55: hard | G55: In WACHEM, which samples have platinum-group enrichment, defined as Pt plus Pd above 50 ppb? Report both values, their sum and the lithology. | H55: 151 | I55: NS4-023.csv | N55: Pass | O55: Yes | T55: N/A | U55: Yes | W55: Pass | X55: N/A | Y55: Pass | Z55: Pass | AA55: Yes | AB55: Pass | AD55: N/A | AE55: N/A | AF55: Yes | AG55: Pass | AM55: test_ns4_questions.py::test_ns4_023_recomputes_wachem_platinum_group_enrichment | AN55: Independent WACHEM filtering reproduced all 151 Pt+Pd rows strictly above 50 ppb, with sums from 50.5 to 2,082 ppb. Six exact-50 rows are correctly excluded by the strict threshold. Evidence: test_ns4_questions.py::test_ns4_023_recomputes_wachem_platinum_group_enrichment (PASS). | AO55: 151 条 Pt+Pd>50 ppb 的结果可复现，范围 50.5–2,082；等于 50 的六条按严格阈值正确排除。 | AQ55: Ziyue_GeoQueryBench_New_Query_Error_Report(1).xlsx
A56: Ziyue | B56: NS4-026 | C56: NS | E56: SQL | F56: hard | G56: Data quality audit: which WAMEX reports appear to have recorded soil gold in the wrong unit? Flag reports whose median soil gold exceeds 100 ppm, which is geologically impossible for soil, and show what the values would be if they were actually ppb. | H56: 6 | I56: NS4-026.csv | N56: Fail | O56: Yes | T56: N/A | U56: Yes | W56: Fail | X56: N/A | Y56: Pass | Z56: Pass | AA56: No | AB56: Fail | AD56: N/A | AE56: Yes | AF56: Yes | AG56: Fail | AM56: test_ns4_questions.py::test_ns4_026_corrected_value_column_uses_its_actual_unit | AN56: The six flagged WAMEX reports and stated-value statistics reproduce. However, dividing a numeric value recorded as ppm by 1,000 gives the ppm equivalent under the hypothesis that the number was actually entered in ppb. Gold places those converted values (for example 23.1685 ppm) under median_if_actually_ppb, which is a unit-label contradiction and can cause a further thousand-fold misinterpretation. Evidence: report test PASS; test_ns4_questions.py::test_ns4_026_corrected_value_column_uses_its_actual_unit (XFAIL). | AO56: 六个疑似错单位报告可复现，但除以 1,000 后得到的是 ppm 等价值，Gold 却将列命名为 ppb，单位标签错误。 | AQ56: Ziyue_GeoQueryBench_New_Query_Error_Report(1).xlsx
A57: Ziyue | B57: NS4-027 | C57: NS | E57: SQL | F57: easy | G57: Among the rock chips, where does copper run more than ten times zinc? Give the two numbers and the factor. | H57: 15715 | I57: NS4-027.csv | N57: Pass | O57: Yes | T57: N/A | U57: Yes | W57: Pass | X57: N/A | Y57: Pass | Z57: Pass | AA57: Yes | AB57: Pass | AD57: N/A | AE57: Yes | AF57: Yes | AG57: Pass with note | AM57: test_ns4_questions.py::test_ns4_027_recomputes_rock_chip_copper_zinc_ratios | AN57: Independent rock-chip filtering reproduced 15,715 unique sample rows with raw Cu/Zn >10 and the reported ratios (allowing the documented SQL versus pandas half-rounding difference at 0.01). Ratios up to 2,684,563.58 are driven by extremely small positive Zn values and require detection-limit/unit scrutiny. Evidence: test_ns4_questions.py::test_ns4_027_recomputes_rock_chip_copper_zinc_ratios (PASS). | AO57: 15,715 个唯一样品及 Cu/Zn>10 结果可复现；极端比值来自极小正 Zn 值，需结合检出限和单位审查。 | AQ57: Ziyue_GeoQueryBench_New_Query_Error_Report(1).xlsx
A58: Ziyue | B58: NS4-039 | C58: NS | E58: SQL | F58: medium | G58: In groundwater, does chloride track sodium as it would in evaporated seawater? Give their medians and the molar ratio. | H58: 1 | I58: NS4-039.csv | N58: Pass | O58: Yes | T58: N/A | U58: Yes | W58: Pass | X58: N/A | Y58: Pass | Z58: Pass | AA58: Yes | AB58: Pass | AD58: N/A | AE58: Yes | AF58: Yes | AG58: Pass with note | AM58: test_ns4_questions.py::test_ns4_039_recomputes_groundwater_chloride_sodium_pairwise_ratio | AN58: Independent positive-pair filtering reproduced n=26,194, median Na 157 mg/L, median Cl 248 mg/L, median pairwise molar ratio 1.075 and 14,196 ratios between 1.0 and 1.35. The pairwise median is a valid defined statistic but differs from the ratio of marginal medians (about 1.024), so the definition must remain explicit. Evidence: test_ns4_questions.py::test_ns4_039_recomputes_groundwater_chloride_sodium_pairwise_ratio (PASS). | AO58: 26,194 对数据及成对摩尔比中位数 1.075 均正确；它不同于两个总体中位数之比，需保留定义说明。 | AQ58: Ziyue_GeoQueryBench_New_Query_Error_Report(1).xlsx
A59: Ziyue | B59: NS4-050 | C59: NS | E59: GeoPandas | F59: easy | G59: How many surface samples inside greenstone belts have both nickel and copper measured? | H59: 12 | I59: NS4-050.csv | N59: Fail | O59: Yes | T59: N/A | U59: Yes | W59: Pass | X59: Pass | Y59: Fail | Z59: Fail | AA59: No | AB59: Fail | AD59: Pass | AE59: Yes | AF59: No | AG59: Fail | AM59: test_ns4_questions.py::test_ns4_050_returns_complete_total_inside_greenstone_belts | AN59: Gold returns the 12 largest belt groups plus unrequested medians, whose n_samples sum to 1,702,262. The question asks how many surface samples inside greenstone belts have both elements measured; the complete unique qualifying total is 1,706,106 across 22 groups, so top-12 truncation omits 3,844 samples and does not provide the requested total. Evidence: package test PASS; test_ns4_questions.py::test_ns4_050_returns_complete_total_inside_greenstone_belts (XFAIL). | AO59: 题目要求完整总数，Gold 却返回前 12 个带及额外中位数，少计 3,844 个合格样品；完整唯一总数应为 1,706,106。 | AQ59: Ziyue_GeoQueryBench_New_Query_Error_Report(1).xlsx
A60: Ziyue | B60: NS4-053 | C60: NS | E60: GeoPandas | F60: medium | G60: Compare the nickel to copper ratio inside greenstone belts against outside them. | H60: 2 | I60: NS4-053.csv | N60: Pass | O60: Yes | T60: N/A | U60: Yes | W60: Pass | X60: Pass | Y60: Pass | Z60: Pass | AA60: Yes | AB60: Pass | AD60: Pass | AE60: Yes | AF60: Yes | AG60: Pass with note | AM60: test_ns4_questions.py::test_ns4_053_reports_both_inside_and_outside_ratio_summaries | AN60: The two rows are internally coherent: within the belt bounding rectangle, 1,700,173 inside and 1,635,870 outside samples pass the positive-value and <100,000 filters; both median and geometric-mean Ni/Cu ratios are higher inside. The outside category means outside polygons but still inside the belts' total bounding rectangle, not statewide outside, and this scope should be disclosed. Evidence: test_ns4_questions.py::test_ns4_053_reports_both_inside_and_outside_ratio_summaries (PASS). | AO60: 两组比值结果内部一致，但 outside 仅指绿岩带总外包矩形内且不在多边形中的样品，不是全州带外，需说明范围。 | AQ60: Ziyue_GeoQueryBench_New_Query_Error_Report(1).xlsx
A61: Ziyue | B61: NS5-016 | C61: NS | E61: Visualisation | F61: medium | G61: Plot the number of groundwater analyses sampled per year as a bar chart. | H61: 1 | I61: NS5-016.png | N61: N/A | O61: Yes | T61: N/A | U61: Yes | W61: Pass | X61: N/A | Y61: Pass | Z61: Pass | AA61: Yes | AB61: Pass | AD61: N/A | AE61: Yes | AF61: No | AG61: Pass with note | AM61: test_ns5_questions.py::test_ns5_016_year_counts_support_readable_groundwater_bar_chart | AN61: Independent date parsing reproduced yearly counts 52, 255, 325, 312 and 21 for 2002-2006 and confirmed 965 dated rows. The bar-chart PNG is readable and explicitly states 965 dated of 40,581 total analyses, so the severe date missingness is visible rather than hidden. Evidence: test_ns5_questions.py::test_ns5_016_year_counts_support_readable_groundwater_bar_chart (PASS). | AO61: 年度柱状图与 965 条有日期记录可复现，并明确标出总计 40,581 条中的日期缺失情况。 | AQ61: Ziyue_GeoQueryBench_New_Query_Error_Report(1).xlsx
A62: Ziyue | B62: NS5-017 | C62: NS | E62: Visualisation | F62: hard | G62: Draw a choropleth of surface-sample count per 1:250k map sheet, using a logarithmic colour scale. | H62: 1 | I62: NS5-017.png | N62: N/A | O62: Yes | T62: N/A | U62: Yes | W62: Pass | X62: Pass | Y62: Pass | Z62: Pass | AA62: Yes | AB62: Pass | AD62: Pass | AE62: Yes | AF62: No | AG62: Pass with note | AM62: test_ns5_questions.py::test_ns5_017_choropleth_inputs_and_png_are_well_formed | AN62: The map-sheet and 7,516,543-sample inputs have compatible spatial structure, and the supplied choropleth PNG is readable, nonblank, uses a log-labelled colour scale and renders zero-sample sheets separately. The map counts UIDs after a global de-duplication across sheet overlaps, so boundary/overlap assignment remains a minor methodology caveat. Evidence: test_ns5_questions.py::test_ns5_017_choropleth_inputs_and_png_are_well_formed (PASS). | AO62: 分幅、样品输入及对数色标地图均有效；但跨图幅全局 UID 去重对重叠边界的归属仍是方法说明项。 | AQ62: Ziyue_GeoQueryBench_New_Query_Error_Report(1).xlsx
A63: Ziyue | B63: NS5-024 | C63: NS | E63: Visualisation | F63: hard | G63: Dual-axis plot for soil gold in 0.1-ppm bins up to 1 ppm: bars for sample count, and a line for the cumulative share of total contained gold. | H63: 1 | I63: NS5-024.png | N63: N/A | O63: Yes | T63: N/A | U63: Yes | W63: Pass | X63: N/A | Y63: Pass | Z63: Pass | AA63: Yes | AB63: Pass | AD63: N/A | AE63: N/A | AF63: No | AG63: Pass | AM63: test_ns5_questions.py::test_ns5_024_soil_gold_histogram_and_cumulative_metal_are_reproducible | AN63: Independent soil filtering and 0.1 ppm histogramming verified ten bins, complete sample allocation, monotonic cumulative contained-gold share and a final share of one. The dual-axis PNG is readable and labels both axes. Evidence: test_ns5_questions.py::test_ns5_024_soil_gold_histogram_and_cumulative_metal_are_reproducible (PASS). | AO63: 0–1 ppm 的十个分箱、样品计数及累计含金量曲线逻辑正确，双轴 PNG 可读。 | AQ63: Ziyue_GeoQueryBench_New_Query_Error_Report(1).xlsx
A64: Ziyue | B64: NS5-027 | C64: NS | E64: Visualisation | F64: hard | G64: Map soil gold across the Kalgoorlie box (longitude 121.2 to 121.8, latitude -31.0 to -30.5) so that the spatial pattern of the anomalies is actually visible. | H64: 1 | I64: NS5-027.png | N64: N/A | O64: Yes | T64: Pass | U64: Yes | W64: Pass | X64: Pass | Y64: Pass | Z64: Pass | AA64: Yes | AB64: Pass | AD64: Pass | AE64: Yes | AF64: No | AG64: Pass with note | AM64: test_ns5_questions.py::test_ns5_027_kalgoorlie_log_map_quantiles_and_count_are_reproducible | AN64: Independent bbox and positive-value filtering reproduced 66,943 soil samples, the 1st percentile 0.00001 ppm, 99.9th percentile 13 ppm and maximum 537,099.97 ppm. LogNorm uses the two percentiles for colour saturation, making spatial structure visible while extreme values remain in the data; the PNG is readable. Evidence: test_ns5_questions.py::test_ns5_027_kalgoorlie_log_map_quantiles_and_count_are_reproducible (PASS). | AO64: 66,943 个正值样品及色标分位点可复现；极端值仍保留但颜色在分位端点饱和，空间结构可见。 | AQ64: Ziyue_GeoQueryBench_New_Query_Error_Report(1).xlsx
... A70: Ziyue | B70: NS5-053 | C70: NS | E70: SQL | F70: medium | G70: Prepare data for a scatter of arsenic against gold: a random sample of 5000 soil pairs with both values. | H70: 5000 | I70: NS5-053.csv | N70: Pass | O70: Yes | T70: Pass | U70: Yes | W70: Pass | X70: N/A | Y70: Pass | Z70: Pass | AA70: Yes | AB70: Pass | AD70: N/A | AE70: Yes | AF70: No | AG70: Pass with note | AM70: test_ns5_questions.py::test_ns5_053_random_scatter_sample_obeys_filters_but_has_no_provenance_key | AN70: All 5,000 delivered rows satisfy 0<Au<100 and 0<As<100,000 and are drawn from an eligible pool of 2,118,301 soil pairs. However, USING SAMPLE has no seed and the CSV omits UID, so the exact sample cannot be rerun or traced to source rows; this is a reproducibility/provenance caveat rather than a filter error. Evidence: test_ns5_questions.py::test_ns5_053_random_scatter_sample_obeys_filters_but_has_no_provenance_key (PASS). | AO70: 5,000 行均符合筛选并来自 2,118,301 个候选对；但无随机种子且不含 UID，无法精确复现或追溯。 | AQ70: Ziyue_GeoQueryBench_New_Query_Error_Report(1).xlsx
A71: Sarwesh | B71: CD1-016 | C71: CD | E71: python | F71: easy | G71: In the Kambalda box (lon 121.5-121.8, lat -31.3 to -31.1), how many surface samples and how many drill holes are there? | H71: 1 | I71: Found | J71: Generated | K71: 1 | L71: 1 | M71: True | N71: True | O71: True | P71: 0 | Q71: 0 | R71: 0 | S71: None | T71: 0 | V71: PASS | Z71: Pass | AB71: Pass | AC71: Pass | AD71: Pass | AG71: Pass | AH71: FALSE | AN71: The supplied python code executes successfully and the independent rerun reproduces the supplied 1-row result exactly: row count, columns and values all match. No duplicate rows were found. No negative-value or sentinel-value issues were identified. | AQ71: Sarwesh_GeoQueryBench_New_Query_Error_Report(1).xlsx
A72: Sarwesh | B72: CD1-017 | C72: CD | E72: geopandas | F72: medium | G72: How many drill holes and how many surface samples fall inside the Hamersley Basin? | H72: 1 | I72: CD1-017.csv | J72: CD1-017_rerun.csv | K72: 1 | L72: 1 | M72: True | N72: True | O72: True | P72: 0 | Q72: 0 | R72: 0 | S72: None | T72: 0 | V72: PASS | Z72: Pass | AB72: Pass | AC72: Pass | AD72: Pass | AG72: Pass | AH72: FALSE | AN72: The supplied geopandas code executes successfully and the independent rerun reproduces the supplied 1-row result exactly: row count, columns and values all match. No duplicate rows were found. No negative-value or sentinel-value issues were identified. | AQ72: Sarwesh_GeoQueryBench_New_Query_Error_Report(1).xlsx
A73: Sarwesh | B73: CD1-023 | C73: CD | E73: geopandas | F73: hard | G73: Is every operating gold mine site accompanied by nearby surface sampling? Report how many operating gold sites have at least one surface sample within 1 km, and how many have none. | H73: 1 | I73: CD1-023.csv | J73: CD1-023_rerun.csv | K73: 1 | L73: 1 | M73: True | N73: True | O73: True | P73: 0 | Q73: 0 | R73: 0 | S73: None | T73: 0 | V73: PASS | Z73: Pass | AB73: Pass | AC73: Pass | AD73: Pass | AG73: Pass | AH73: FALSE | AN73: The supplied geopandas code executes successfully and the independent rerun reproduces the supplied 1-row result exactly: row count, columns and values all match. No duplicate rows were found. No negative-value or sentinel-value issues were identified. | AQ73: Sarwesh_GeoQueryBench_New_Query_Error_Report(1).xlsx
A74: Sarwesh | B74: CD1-024 | C74: CD | E74: geopandas | F74: hard | G74: Three-layer join in the Kalgoorlie-Kambalda box (lon 121.0-122.0, lat -32.0 to -30.5): how many soil samples are simultaneously within 2 km of a drill hole AND within 1 km of a mapped fault? | H74: 1 | I74: CD1-024.csv | J74: CD1-024_rerun.csv | K74: 1 | L74: 1 | M74: True | N74: True | O74: True | P74: 0 | Q74: 0 | R74: 0 | S74: None | T74: 0 | V74: PASS | Z74: Pass | AB74: Pass | AC74: Pass | AD74: Pass | AG74: Pass | AH74: FALSE | AN74: The supplied geopandas code executes successfully and the independent rerun reproduces the supplied 1-row result exactly: row count, columns and values all match. No duplicate rows were found. No negative-value or sentinel-value issues were identified. | AQ74: Sarwesh_GeoQueryBench_New_Query_Error_Report(1).xlsx
A75: Sarwesh | B75: CD1-026 | C75: CD | E75: geopandas | F75: hard | G75: In the Kalgoorlie-Kambalda region, how many soil gold anomalies (above 100 ppb) have a drill hole within 500 m that returns a significant intercept ΓÇö at least 4 m composited at 0.5 g/t Au or better, allowing up to 2 m of internal dilution? Do not use any pre-computed maximum-grade table. | H75: 1 | I75: CD1-026.csv | J75: CD1-026_rerun.csv | K75: 1 | L75: 1 | M75: True | N75: True | O75: False | P75: 0 | Q75: 0 | R75: 0 | S75: None | T75: 0 | V75: CHECK REQUIRED | Z75: Fail | AB75: Fail | AC75: Pass | AD75: Fail | AG75: Fail | AH75: TRUE | AN75: The supplied GeoPandas code executes successfully, but its own logged comparison shows a genuine value mismatch: the independent rerun reports n_hole_has_significant_intercept = 1,832 against the supplied 1,821, out of 15,180 soil-Au anomalies in the Kalgoorlie-Kambalda region (n_anomalies_in_region and n_with_hole_within_500m both match exactly at 15,180 and the log's own row count/column shape). The validator flags this itself as 'Supplied query runs: CHECK REQUIRED'. The root cause is a non-deterministic nearest-neighbour tie-break: gpd.sjoin_nearest(g, holes, max_distance=500, ...).drop_duplicates('uid') keeps one arbitrary hole per anomaly when multiple holes are equally near, and the code then reads an attribute (best_intercept_gpt, via near.hole_id.map(best)) from whichever tied hole survived the drop_duplicates call, rather than testing only existence. Because the kept tie depends on row order rather than a documented rule, the count of anomalies whose nearest hole clears the 0.5 g/t / 4 m / 2 m-dilution significant-intercept test is not reproducible between runs. | AQ75: Sarwesh_GeoQueryBench_New_Query_Error_Report(1).xlsx
A76: Sarwesh | B76: CD1-029 | C76: CD | E76: sql | F76: hard | G76: In a single SQL query, report how many drill holes and how many surface samples fall inside the Hamersley Basin. | H76: 1 | I76: Found | J76: Generated | K76: 1 | L76: 1 | M76: True | N76: True | O76: True | P76: 0 | Q76: 0 | R76: 0 | S76: None | T76: 0 | V76: PASS | Z76: Pass | AB76: Pass | AC76: Pass | AD76: Pass | AG76: Pass | AH76: FALSE | AN76: The supplied sql code executes successfully and the independent rerun reproduces the supplied 1-row result exactly: row count, columns and values all match. No duplicate rows were found. No negative-value or sentinel-value issues were identified. | AQ76: Sarwesh_GeoQueryBench_New_Query_Error_Report(1).xlsx
A77: Sarwesh | B77: CD1-036 | C77: CD | E77: sql | F77: medium | G77: Which 1:250 000 map sheets contain the most surface samples? Give the top ten with sheet name and sample count. | H77: 10 | I77: Found | J77: Generated | K77: 10 | L77: 10 | M77: True | N77: True | O77: True | P77: 0 | Q77: 0 | R77: 0 | S77: None | T77: 0 | V77: PASS | Z77: Pass | AB77: Pass | AC77: Pass | AD77: Pass | AG77: Pass | AH77: FALSE | AN77: The supplied sql code executes successfully and the independent rerun reproduces the supplied 10-row result exactly: row count, columns and values all match. No duplicate rows were found. No negative-value or sentinel-value issues were identified. | AQ77: Sarwesh_GeoQueryBench_New_Query_Error_Report(1).xlsx
A78: Sarwesh | B78: CD1-038 | C78: CD | E78: sql | F78: easy | G78: Within the Kalgoorlie box (longitude 121.0 to 122.0, latitude -32.0 to -30.5), how many surface samples fall inside each greenstone belt? | H78: 2 | I78: Found | J78: Generated | K78: 2 | L78: 2 | M78: True | N78: True | O78: True | P78: 0 | Q78: 0 | R78: 0 | S78: None | T78: 0 | V78: PASS | Z78: Pass | AB78: Pass | AC78: Pass | AD78: Pass | AG78: Pass | AH78: FALSE | AN78: The supplied sql code executes successfully and the independent rerun reproduces the supplied 2-row result exactly: row count, columns and values all match. No duplicate rows were found. No negative-value or sentinel-value issues were identified. | AQ78: Sarwesh_GeoQueryBench_New_Query_Error_Report(1).xlsx
A79: Sarwesh | B79: CD1-043 | C79: CD | E79: sql | F79: medium | G79: How many surface samples are within 500 m of a drill hole in the Ravensthorpe region? | H79: 1 | I79: Found | J79: Generated | K79: 1 | L79: 1 | M79: True | N79: True | O79: True | P79: 0 | Q79: 0 | R79: 0 | S79: None | T79: 0 | V79: PASS | Z79: Pass | AB79: Pass | AC79: Pass | AD79: Pass | AG79: Pass | AH79: FALSE | AN79: The supplied sql code executes successfully and the independent rerun reproduces the supplied 1-row result exactly: row count, columns and values all match. No duplicate rows were found. No negative-value or sentinel-value issues were identified. | AQ79: Sarwesh_GeoQueryBench_New_Query_Error_Report(1).xlsx
A80: Sarwesh | B80: CD2-021 | C80: CD | E80: geopandas | F80: hard | G80: Does mapped bedrock geology agree with what was drilled? For ultramafic-mapped polygons, what share of the drill holes inside them logged an ultramafic lithology code? | H80: 1 | I80: CD2-021.csv | J80: CD2-021_rerun.csv | K80: 1 | L80: 1 | M80: True | N80: True | O80: True | P80: 0 | Q80: 0 | R80: 0 | S80: None | T80: 0 | V80: PASS | Z80: Pass | AB80: Pass | AC80: Pass | AD80: Pass | AG80: Pass | AH80: FALSE | AN80: The supplied geopandas code executes successfully and the independent rerun reproduces the supplied 1-row result exactly: row count, columns and values all match. No duplicate rows were found. No negative-value or sentinel-value issues were identified. | AQ80: Sarwesh_GeoQueryBench_New_Query_Error_Report(1).xlsx
A81: Sarwesh | B81: CD2-028 | C81: CD | E81: sql | F81: hard | G81: Without using any spatial extension or spatial function, count the stream sediment samples within 20 km of Kambalda townsite (longitude 121.62, latitude -31.21). Compute great-circle distance in plain SQL. | H81: 1 | I81: Found | J81: Generated | K81: 1 | L81: 1 | M81: True | N81: True | O81: True | P81: 0 | Q81: 0 | R81: 0 | S81: None | T81: 0 | V81: PASS | Z81: Pass | AB81: Pass | AC81: Pass | AD81: Pass | AG81: Pass | AH81: FALSE | AN81: The supplied sql code executes successfully and the independent rerun reproduces the supplied 1-row result exactly: row count, columns and values all match. No duplicate rows were found. No negative-value or sentinel-value issues were identified. | AQ81: Sarwesh_GeoQueryBench_New_Query_Error_Report(1).xlsx
A82: Sarwesh | B82: CD2-031 | C82: CD | E82: geopandas | F82: hard | G82: Take the Kambalda block (121.5 to 121.8 east, -31.3 to -31.1 south). Where soil nickel tops 500 ppm, does the closest hole inside a kilometre also carry better than one percent nickel? Break it down into agrees, disagrees, and nothing drilled nearby. | H82: 3 | I82: CD2-031.csv | J82: CD2-031_rerun.csv | K82: 3 | L82: 3 | M82: True | N82: True | O82: True | P82: 0 | Q82: 0 | R82: 0 | S82: None | T82: 0 | V82: PASS | Z82: Pass | AB82: Pass | AC82: Pass | AD82: Pass | AG82: Pass with note | AH82: FALSE | AN82: The supplied GeoPandas code executes successfully and the rerun reproduces the supplied three-row result exactly (row count, columns and values all match). However, the code uses the identical structural pattern already CONFIRMED unstable elsewhere in this same assigned set (CD1-026): gpd.sjoin_nearest(g, maxg, max_distance=1000, ...).drop_duplicates('uid') followed by reading the joined hole_ni attribute of whichever tied nearest maxgrade point survived the drop_duplicates call, with no documented tie-break rule. In this smaller Kambalda box the one execution captured in the log happened to match the supplied classification (agrees/disagrees/no_hole_within_1km counts identical), which suggests either no ties exist among drillhole_maxgrade points within 1 km of these anomalies, or any ties that exist do not straddle the >1% Ni classification threshold — but neither has been independently confirmed. Given that the same code shape produced a materially different answer in CD1-026, this query's exact match should not be read as proof the tie-break issue does not apply here. | AQ82: Sarwesh_GeoQueryBench_New_Query_Error_Report(1).xlsx
... A140: Sarwesh | B140: NS5-054 | C140: NS | E140: viz | F140: hard | G140: Draw the two trilinear fields of a Piper diagram for the groundwater analyses: cations and anions in milliequivalent percent. | H140: N/A — image output | I140: NS5-054.png | J140: NS5-054_rerun.png | K140: N/A — image output | L140: N/A — image output | M140: N/A — image output | N140: N/A — image output | O140: N/A — image output | P140: N/A — image output | Q140: N/A — image output | R140: N/A — image output | S140: N/A — image output | T140: N/A — image output | V140: PASS | Z140: Pass | AB140: Pass | AC140: Pass | AD140: Pass | AG140: Pass | AH140: FALSE | AN140: The code executes successfully and an independent rerun PNG was generated (NS5-054_rerun.png alongside the supplied NS5-054.png); both exist on disk. Exact pixel equality is not expected or required. The supplied gold image was visually inspected against the question text: the chart/map type, data selection, and labelling appear to genuinely answer what was asked, with no readability, mislabelling, or filtering problem identified. This is a visual sanity check of the gold image, not a pixel-level or pointwise data audit of every plotted value. | AQ140: Sarwesh_GeoQueryBench_New_Query_Error_Report(1).xlsx
A141: Chaitanya | B141: CD1-020 | C141: CD | D141: CD-1 | E141: geopandas | F141: hard | G141: Cross-database: how many GSWA WACHEM reference samples lie within 2 km of an A-database collar, broken down by the collar's region? | H141: 4 | I141: CD1-020.csv | K141: 4 | M141: Match | U141: Yes | AG141: Reference-only | AI141: Reference checked; not rerun | AJ141: Not independently compared | AK141: Not independently regenerated. | AL141: Reference file exists and its data-row count was checked against Expected Rows; query result was not independently regenerated. | AP141: 4 | AQ141: GeoQueryBench_Chaitanya_Error_Report_Reference_Style(1).xlsx
A142: Chaitanya | B142: CD1-028 | C142: CD | D142: CD-1 | E142: sql | F142: hard | G142: Using SQL spatial functions, count the rock chip samples lying within 2 km of a MINEDEX site whose primary commodity is gold. | H142: 1 | I142: CD1-028.csv | K142: 1 | M142: Match | U142: Yes | AG142: Reference-only | AI142: Reference checked; not rerun | AJ142: Not independently compared | AK142: Not independently regenerated. | AL142: Reference file exists and its data-row count was checked against Expected Rows; query result was not independently regenerated. | AP142: 0.2 | AQ142: GeoQueryBench_Chaitanya_Error_Report_Reference_Style(1).xlsx
A143: Chaitanya | B143: CD1-031 | C143: CD | D143: CD-1 | E143: geopandas | F143: hard | G143: How many creek-sediment samples sit close to a hole that hit better than one percent nickel? Close means half a kilometre. | H143: 1 | I143: CD1-031.csv | K143: 1 | M143: Match | U143: Yes | AG143: Reference-only | AI143: Reference checked; not rerun | AJ143: Not independently compared | AK143: Not independently regenerated. | AL143: Reference file exists and its data-row count was checked against Expected Rows; query result was not independently regenerated. | AP143: 7.9 | AQ143: GeoQueryBench_Chaitanya_Error_Report_Reference_Style(1).xlsx
A144: Chaitanya | B144: CD1-039 | C144: CD | D144: CD-1 | E144: sql | F144: medium | G144: Within the Kalgoorlie box (longitude 121.0 to 122.0, latitude -32.0 to -30.5), give each greenstone belt's surface sample count, drill hole count, and the ratio between them. | H144: 2 | I144: CD1-039.csv | K144: 2 | M144: Match | U144: Yes | AG144: Reference-only | AI144: Reference checked; not rerun | AJ144: Not independently compared | AK144: Not independently regenerated. | AL144: Reference file exists and its data-row count was checked against Expected Rows; query result was not independently regenerated. | AP144: 83.6 | AQ144: GeoQueryBench_Chaitanya_Error_Report_Reference_Style(1).xlsx
A145: Chaitanya | B145: CD1-044 | C145: CD | D145: CD-1 | E145: sql | F145: easy | G145: Which sedimentary basins contain drill holes, and how many in each? | H145: 4 | I145: CD1-044.csv | K145: 4 | M145: Match | U145: Yes | AG145: Reference-only | AI145: Reference checked; not rerun | AJ145: Not independently compared | AK145: Not independently regenerated. | AL145: Reference file exists and its data-row count was checked against Expected Rows; query result was not independently regenerated. | AP145: 33.9 | AQ145: GeoQueryBench_Chaitanya_Error_Report_Reference_Style(1).xlsx
A146: Chaitanya | B146: CD1-049 | C146: CD | D146: CD-1 | E146: sql | F146: medium | G146: How many holes sit inside a mapped geological unit in the Kalgoorlie box? | H146: 2 | I146: CD1-049.csv | K146: 2 | M146: Match | U146: Yes | AG146: Reference-only | AI146: Reference checked; not rerun | AJ146: Not independently compared | AK146: Not independently regenerated. | AL146: Reference file exists and its data-row count was checked against Expected Rows; query result was not independently regenerated. | AP146: 79.5 | AQ146: GeoQueryBench_Chaitanya_Error_Report_Reference_Style(1).xlsx
A147: Chaitanya | B147: CD2-018 | C147: CD | D147: CD-2 | E147: python | F147: easy | G147: Which of the four A-database regions has the most surface samples per drill hole in its bounding box? | H147: 4 | I147: CD2-018.csv | K147: 4 | M147: Match | U147: Yes | AG147: Mismatch | AI147: Independently rerun | AJ147: Mismatch | AK147: Generated 4 regional rows; count differences listed in finding. | AL147: Independent rerun differs from gold sample counts by region (R4 64,164 vs 64,514; R2 208,355 vs 208,366; R1 534,979 vs 534,994; R3 1,300 vs 1,302). Rerun used collar coordinate extents as regional boxes; confirm the intended regional bounding boxes before replacing the supplied gold values. | AP147: 0.7 | AQ147: GeoQueryBench_Chaitanya_Error_Report_Reference_Style(1).xlsx
A148: Chaitanya | B148: CD2-022 | C148: CD | D148: CD-2 | E148: geopandas | F148: hard | G148: How strong is the link between surface and subsurface gold? For soil samples within 500 m of a hole, compute the correlation between the sample's gold and that hole's maximum downhole gold, using log-transformed values. | H148: 1 | I148: CD2-022.csv | K148: 1 | M148: Match | U148: Yes | AG148: Reference-only | AI148: Reference checked; not rerun | AJ148: Not independently compared | AK148: Not independently regenerated. | AL148: Reference file exists and its data-row count was checked against Expected Rows; query result was not independently regenerated. | AP148: 364.5 | AQ148: GeoQueryBench_Chaitanya_Error_Report_Reference_Style(1).xlsx
A149: Chaitanya | B149: CD2-026 | C149: CD | D149: CD-2 | E149: geopandas | F149: hard | G149: Two ways of describing what a hole found: for soil gold anomalies with a hole within 1 km in the Kalgoorlie-Kambalda region, compute the correlation between the surface value and (a) the hole's single highest assay, and (b) the hole's best 4 m composited intercept. Report both correlations and say whether the two give the same conclusion. | H149: 1 | I149: CD2-026.csv | K149: 1 | M149: Match | U149: Yes | AG149: Reference-only | AI149: Reference checked; not rerun | AJ149: Not independently compared | AK149: Not independently regenerated. | AL149: Reference file exists and its data-row count was checked against Expected Rows; query result was not independently regenerated. | AP149: 15.5 | AQ149: GeoQueryBench_Chaitanya_Error_Report_Reference_Style(1).xlsx
A150: Chaitanya | B150: CD2-033 | C150: CD | D150: CD-2 | E150: refusal | F150: hard | G150: What is the ore reserve of the Kambalda nickel operation, in tonnes and grade? | I150: CD2-033.txt | K150: TEXT | M150: N/A — image/text output | U150: Yes | AG150: Valid refusal | AI150: Independent schema/refusal check | AJ150: Valid refusal | AK150: Database schema independently checked; reserve tonnes and grade are not stored in the supplied database. | AL150: The correct response is to refuse the requested reserve tonnes/grade: the supplied mineral_site schema has no reserve or resource estimate fields. | AP150: 0 | AQ150: GeoQueryBench_Chaitanya_Error_Report_Reference_Style(1).xlsx
A151: Chaitanya | B151: CD2-039 | C151: CD | D151: CD-2 | E151: sql | F151: easy | G151: For copper, compare the number of usable measurements and the median grade between the surface and drill-hole databases. | H151: 2 | I151: CD2-039.csv | K151: 2 | M151: Match | U151: Yes | AG151: Match | AI151: Independently rerun | AJ151: Match | AK151: 2 rows; exact match. | AL151: Rerun output matches supplied gold after ignoring row order and applying reference display precision. | AP151: 0.4 | AQ151: GeoQueryBench_Chaitanya_Error_Report_Reference_Style(1).xlsx
A152: Chaitanya | B152: CD2-040 | C152: CD | D152: CD-2 | E152: sql | F152: medium | G152: Do the surface and drill-hole databases agree on which elements are best measured? Rank the ten most-measured elements on each side. | H152: 8 | I152: CD2-040.csv | K152: 8 | M152: Match | U152: Yes | AG152: Reference-only | AI152: Reference checked; not rerun | AJ152: Not independently compared | AK152: Not independently regenerated. | AL152: Reference file exists and its data-row count was checked against Expected Rows; query result was not independently regenerated. | AP152: 0.4 | AQ152: GeoQueryBench_Chaitanya_Error_Report_Reference_Style(1).xlsx
A153: Chaitanya | B153: CD2-045 | C153: CD | D153: CD-2 | E153: viz | F153: medium | G153: Draw overlaid log histograms comparing gold in surface samples against gold in drill hole assays. | H153: 1 | I153: CD2-045.png | K153: IMAGE | M153: N/A — image/text output | U153: Yes | AG153: Reference-only | AI153: Reference checked; not rerun | AJ153: Not independently compared | AK153: Not independently regenerated. | AL153: Reference PNG is present; independent image regeneration/comparison was not performed. | AP153: 1.5 | AQ153: GeoQueryBench_Chaitanya_Error_Report_Reference_Style(1).xlsx
A154: Chaitanya | B154: CD2-049 | C154: CD | D154: CD-2 | E154: sql | F154: medium | G154: Compare tantalum between surface and drill holes — the drill hole side reports some very high values. Are they credible? | H154: 2 | I154: CD2-049.csv | K154: 2 | M154: Match | U154: Yes | AG154: Reference-only | AI154: Reference checked; not rerun | AJ154: Not independently compared | AK154: Not independently regenerated. | AL154: Reference file exists and its data-row count was checked against Expected Rows; query result was not independently regenerated. | AP154: 0 | AQ154: GeoQueryBench_Chaitanya_Error_Report_Reference_Style(1).xlsx
A155: Chaitanya | B155: CD3-018 | C155: CD | D155: CD-3 | E155: python | F155: medium | G155: Within the Kambalda box (lon 121.5-121.8, lat -31.3 to -31.1), how many soil gold anomalies above 100 ppb are there, and how many drill holes, as a first look at how much follow-up exists? | H155: 1 | I155: CD3-018.csv | K155: 1 | M155: Match | U155: Yes | AG155: Match | AI155: Independently rerun | AJ155: Match | AK155: 1 row; exact match (36 anomalies, 28,421 holes, 789.47 holes per anomaly). | AL155: Rerun output matches supplied gold after ignoring row order and applying reference display precision. | AP155: 10.8 | AQ155: GeoQueryBench_Chaitanya_Error_Report_Reference_Style(1).xlsx
A156: Chaitanya | B156: CD3-019 | C156: CD | D156: CD-3 | E156: geopandas | F156: hard | G156: Which mapped ultramafic polygons contain nickel-anomalous soil samples (above 500 ppm) but have no drill hole inside them? List the ten largest such polygons. | H156: 10 | I156: CD3-019.csv | K156: 10 | M156: Match | U156: Yes | AG156: Reference-only | AI156: Reference checked; not rerun | AJ156: Not independently compared | AK156: Not independently regenerated. | AL156: Reference file exists and its data-row count was checked against Expected Rows; query result was not independently regenerated. | AP156: 15 | AQ156: GeoQueryBench_Chaitanya_Error_Report_Reference_Style(1).xlsx
A157: Chaitanya | B157: CD3-020 | C157: CD | D157: CD-3 | E157: geopandas | F157: hard | G157: Which WAROX field observations that mention mineralisation or gossan have no drill hole within 1 km? List ten examples with the observation notes. | H157: 10 | I157: CD3-020.csv | K157: 10 | M157: Match | U157: Yes | AG157: Reference-only | AI157: Reference checked; not rerun | AJ157: Not independently compared | AK157: Not independently regenerated. | AL157: Reference file has 10 data rows, matching the workbook expectation. The field n_targets_total=885 is a result value, not the file row count. | AP157: 8.6 | AQ157: GeoQueryBench_Chaitanya_Error_Report_Reference_Style(1).xlsx
A158: Chaitanya | B158: CD3-029 | C158: CD | D158: CD-3 | E158: sql | F158: hard | G158: In SQL, count the soil samples with gold above 100 ppb that have no drill collar within 2 km, restricted to the Kalgoorlie-Kambalda box (longitude 121 to 122, latitude -32 to -30.5). | H158: 1 | I158: CD3-029.csv | K158: 1 | M158: Match | U158: Yes | AG158: Reference-only | AI158: Reference checked; not rerun | AJ158: Not independently compared | AK158: Not independently regenerated. | AL158: Reference file exists and its data-row count was checked against Expected Rows; query result was not independently regenerated. | AP158: 0.4 | AQ158: GeoQueryBench_Chaitanya_Error_Report_Reference_Style(1).xlsx
A159: Chaitanya | B159: CD3-034 | C159: CD | D159: CD-3 | E159: geopandas | F159: hard | G159: Find the undrilled gold targets near Kambalda. | H159: 9 | I159: CD3-034.csv | K159: 9 | M159: Match | U159: Yes | AG159: Reference-only | AI159: Reference checked; not rerun | AJ159: Not independently compared | AK159: Not independently regenerated. | AL159: Reference file exists and its data-row count was checked against Expected Rows; query result was not independently regenerated. | AP159: 11.5 | AQ159: GeoQueryBench_Chaitanya_Error_Report_Reference_Style(1).xlsx
A160: Chaitanya | B160: CD3-035 | C160: CD | D160: CD-3 | E160: geopandas | F160: hard | G160: Rank the undrilled soil gold anomalies in the Kambalda box by how promising they are, and show your ranking basis. | H160: 15 | I160: CD3-035.csv | K160: 15 | M160: Match | U160: Yes | AG160: Reference-only | AI160: Reference checked; not rerun | AJ160: Not independently compared | AK160: Not independently regenerated. | AL160: Reference file exists and its data-row count was checked against Expected Rows; query result was not independently regenerated. | AP160: 14.4 | AQ160: GeoQueryBench_Chaitanya_Error_Report_Reference_Style(1).xlsx
A161: Chaitanya | B161: CD3-040 | C161: CD | D161: CD-3 | E161: sql | F161: easy | G161: In the Kalgoorlie-to-Leonora window (longitude 120.5 to 122.5, latitude -32.0 to -28.5), which greenstone belts have surface samples but no drilling at all? | H161: 1 | I161: CD3-040.csv | K161: 1 | M161: Match | U161: Yes | AG161: Reference-only | AI161: Reference checked; not rerun | AJ161: Not independently compared | AK161: Not independently regenerated. | AL161: Reference file exists and its data-row count was checked against Expected Rows; query result was not independently regenerated. | AP161: 144.9 | AQ161: GeoQueryBench_Chaitanya_Error_Report_Reference_Style(1).xlsx
A162: Chaitanya | B162: CD3-043 | C162: CD | D162: CD-3 | E162: sql | F162: medium | G162: Find the pegmatites worth following up for lithium. | H162: 12 | I162: CD3-043.csv | K162: 12 | M162: Match | U162: Yes | AG162: Reference-only | AI162: Reference checked; not rerun | AJ162: Not independently compared | AK162: Not independently regenerated. | AL162: Reference file exists and its data-row count was checked against Expected Rows; query result was not independently regenerated. | AP162: 0.3 | AQ162: GeoQueryBench_Chaitanya_Error_Report_Reference_Style(1).xlsx
A163: Chaitanya | B163: CD3-056 | C163: CD | D163: CD-3 | E163: sql | F163: easy | G163: How many sedimentary basins have no mineral occurrences recorded inside them? | H163: 1 | I163: CD3-056.csv | K163: 1 | M163: Match | U163: Yes | AG163: Reference-only | AI163: Reference checked; not rerun | AJ163: Not independently compared | AK163: Not independently regenerated. | AL163: Reference file exists and its data-row count was checked against Expected Rows; query result was not independently regenerated. | AP163: 1.9 | AQ163: GeoQueryBench_Chaitanya_Error_Report_Reference_Style(1).xlsx
A164: Chaitanya | B164: CD4-018 | C164: CD | D164: CD-4 | E164: viz | F164: hard | G164: Small multiples: for each of the four A-database regions, draw one panel showing drill collars and surface samples in that region's box. | H164: 1 | I164: CD4-018.png | K164: IMAGE | M164: N/A — image/text output | U164: Yes | AG164: Reference-only | AI164: Reference checked; not rerun | AJ164: Not independently compared | AK164: Not independently regenerated. | AL164: Reference PNG is present; independent image regeneration/comparison was not performed. | AP164: 19.3 | AQ164: GeoQueryBench_Chaitanya_Error_Report_Reference_Style(1).xlsx
A165: Chaitanya | B165: CD4-024 | C165: CD | D165: CD-4 | E165: viz | F165: hard | G165: Two-panel scale comparison for the Kalgoorlie-Kambalda box: left, the statewide context with the box outlined; right, the box itself with samples and holes. | H165: 1 | I165: CD4-024.png | K165: IMAGE | M165: N/A — image/text output | U165: Yes | AG165: Reference-only | AI165: Reference checked; not rerun | AJ165: Not independently compared | AK165: Not independently regenerated. | AL165: Reference PNG is present; independent image regeneration/comparison was not performed. | AP165: 14.3 | AQ165: GeoQueryBench_Chaitanya_Error_Report_Reference_Style(1).xlsx
A166: Chaitanya | B166: CD4-027 | C166: CD | D166: CD-4 | E166: viz | F166: easy | G166: Plot surface samples and drill collars for the Leonora-Murrin box (longitude 121.25 to 122.25, latitude -29.5 to -28.75) as two layers on one chart. | H166: 1 | I166: CD4-027.png | K166: IMAGE | M166: N/A — image/text output | U166: Yes | AG166: Reference-only | AI166: Reference checked; not rerun | AJ166: Not independently compared | AK166: Not independently regenerated. | AL166: Reference PNG is present; independent image regeneration/comparison was not performed. | AP166: 8.4 | AQ166: GeoQueryBench_Chaitanya_Error_Report_Reference_Style(1).xlsx
A167: Chaitanya | B167: CD4-030 | C167: CD | D167: CD-4 | E167: viz | F167: hard | G167: Show me whether the gold sits on the faults around Kalgoorlie — I want the fault lines and the drilling on one picture. | H167: 1 | I167: CD4-030.png | K167: IMAGE | M167: N/A — image/text output | U167: Yes | AG167: Reference-only | AI167: Reference checked; not rerun | AJ167: Not independently compared | AK167: Not independently regenerated. | AL167: Reference PNG is present; independent image regeneration/comparison was not performed. | AP167: 3.8 | AQ167: GeoQueryBench_Chaitanya_Error_Report_Reference_Style(1).xlsx
A168: Chaitanya | B168: CD4-034 | C168: CD | D168: CD-4 | E168: viz | F168: medium | G168: Map surface magnesium against the greenstone belts — magnesium should track the ultramafic rocks. | H168: 1 | I168: CD4-034.png | K168: IMAGE | M168: N/A — image/text output | U168: Yes | AG168: Reference-only | AI168: Reference checked; not rerun | AJ168: Not independently compared | AK168: Not independently regenerated. | AL168: Reference PNG is present; independent image regeneration/comparison was not performed. | AP168: 12.1 | AQ168: GeoQueryBench_Chaitanya_Error_Report_Reference_Style(1).xlsx
A169: Chaitanya | B169: CD4-036 | C169: CD | D169: CD-4 | E169: sql | F169: medium | G169: Prepare a table for a two-layer map: per greenstone belt, the belt name, its area in square kilometres, and how many drill holes it contains. | H169: 15 | I169: CD4-036.csv | K169: 15 | M169: Match | U169: Yes | AG169: Reference-only | AI169: Reference checked; not rerun | AJ169: Not independently compared | AK169: Not independently regenerated. | AL169: Reference file exists and its data-row count was checked against Expected Rows; query result was not independently regenerated. | AP169: 119.7 | AQ169: GeoQueryBench_Chaitanya_Error_Report_Reference_Style(1).xlsx
A170: Chaitanya | B170: CD4-045 | C170: CD | D170: CD-4 | E170: sql | F170: easy | G170: Prepare a plot-ready table of greenstone belt names and centroids in the Kalgoorlie box, for map labelling. | H170: 3 | I170: CD4-045.csv | K170: 3 | M170: Match | U170: Yes | AG170: Reference-only | AI170: Reference checked; not rerun | AJ170: Not independently compared | AK170: Not independently regenerated. | AL170: Reference file exists and its data-row count was checked against Expected Rows; query result was not independently regenerated. | AP170: 0 | AQ170: GeoQueryBench_Chaitanya_Error_Report_Reference_Style(1).xlsx
A171: Chaitanya | B171: CD4-046 | C171: CD | D171: CD-4 | E171: geopandas | F171: medium | G171: Prepare 2 km buffers around gold mineral occurrences in the Kalgoorlie box, and count drill holes inside each buffer. | H171: 29 | I171: CD4-046.csv | K171: 29 | M171: Match | U171: Yes | AG171: Reference-only | AI171: Reference checked; not rerun | AJ171: Not independently compared | AK171: Not independently regenerated. | AL171: Reference file exists and its data-row count was checked against Expected Rows; query result was not independently regenerated. | AP171: 0.8 | AQ171: GeoQueryBench_Chaitanya_Error_Report_Reference_Style(1).xlsx
A172: Chaitanya | B172: CD4-050 | C172: CD | D172: CD-4 | E172: geopandas | F172: easy | G172: Prepare clipped layers for a Kambalda map: greenstone belts, faults and mineral occurrences within the box, with feature counts. | H172: 3 | I172: CD4-050.csv | K172: 3 | M172: Match | U172: Yes | AG172: Reference-only | AI172: Reference checked; not rerun | AJ172: Not independently compared | AK172: Not independently regenerated. | AL172: Reference file exists and its data-row count was checked against Expected Rows; query result was not independently regenerated. | AP172: 0.2 | AQ172: GeoQueryBench_Chaitanya_Error_Report_Reference_Style(1).xlsx
A173: Chaitanya | B173: NS1-017 | C173: NS | D173: NS-1 | E173: sql | F173: medium | G173: List the 1:250k map sheets released before 1980, with sheet name, sheet number, release year and the horizontal datum used. | H173: 69 | I173: NS1-017.csv | K173: 69 | M173: Match | U173: Yes | AG173: Match | AI173: Independently rerun | AJ173: Match | AK173: 69 rows; exact match. | AL173: Rerun output matches supplied gold after ignoring row order and applying reference display precision. | AP173: 0 | AQ173: GeoQueryBench_Chaitanya_Error_Report_Reference_Style(1).xlsx
A174: Chaitanya | B174: NS1-020 | C174: NS | D174: NS-1 | E174: sql | F174: hard | G174: List groundwater analyses sampled during 2005, showing bore name, sample date, pH and TDS. | H174: 312 | I174: NS1-020.csv | K174: 312 | M174: Match | U174: Yes | AG174: Match | AI174: Independently rerun | AJ174: Match | AK174: 312 rows; exact match. | AL174: Rerun output matches supplied gold after ignoring row order and applying reference display precision. | AP174: 0 | AQ174: GeoQueryBench_Chaitanya_Error_Report_Reference_Style(1).xlsx
A175: Chaitanya | B175: NS1-031 | C175: NS | D175: NS-1 | E175: sql | F175: easy | G175: How much manganese is in the surface samples? Give the count and median for each sample medium. | H175: 4 | I175: NS1-031.csv | K175: 4 | M175: Match | U175: Yes | AG175: Match | AI175: Independently rerun | AJ175: Match | AK175: 4 rows; exact match after displayed rounding. | AL175: Rerun output matches supplied gold after ignoring row order and applying reference display precision. | AP175: 0.7 | AQ175: GeoQueryBench_Chaitanya_Error_Report_Reference_Style(1).xlsx
A176: Chaitanya | B176: NS1-033 | C176: NS | D176: NS-1 | E176: sql | F176: medium | G176: Which rock chip samples are anomalous in both tantalum and tin? These are pegmatite indicators. | H176: 20 | I176: NS1-033.csv | K176: 20 | M176: Match | U176: Yes | AG176: Reference-only | AI176: Reference checked; not rerun | AJ176: Not independently compared | AK176: Not independently regenerated. | AL176: Reference file exists and its data-row count was checked against Expected Rows; query result was not independently regenerated. | AP176: 0.2 | AQ176: GeoQueryBench_Chaitanya_Error_Report_Reference_Style(1).xlsx
A177: Chaitanya | B177: NS1-042 | C177: NS | D177: NS-1 | E177: sql | F177: hard | G177: Does the aluminium reported as Al2O3 percent agree with the aluminium reported in ppm? Check on the samples that have both. | H177: 1 | I177: NS1-042.csv | K177: 1 | M177: Match | U177: Yes | AG177: Match | AI177: Independently rerun | AJ177: Match | AK177: 1 row; exact match after displayed rounding and Al₂O₃-to-Al factor 0.52925. | AL177: Rerun output matches supplied gold after ignoring row order and applying reference display precision. | AP177: 0 | AQ177: GeoQueryBench_Chaitanya_Error_Report_Reference_Style(1).xlsx
A178: Chaitanya | B178: NS1-048 | C178: NS | D178: NS-1 | E178: sql | F178: easy | G178: Are rare earth elements measured anywhere in this database? Which ones, and in how many samples? | H178: 8 | I178: NS1-048.csv | K178: 8 | M178: Match | U178: Yes | AG178: Match | AI178: Independently rerun | AJ178: Match | AK178: 8 rows; exact match. | AL178: Rerun output matches supplied gold after ignoring row order and applying reference display precision. | AP178: 0 | AQ178: GeoQueryBench_Chaitanya_Error_Report_Reference_Style(1).xlsx
A179: Chaitanya | B179: NS2-022 | C179: NS | D179: NS-2 | E179: sql | F179: medium | G179: What is the typical gold value in soil samples? | H179: 1 | I179: NS2-022.csv | K179: 1 | M179: Match | U179: Yes | AG179: Match | AI179: Independently rerun | AJ179: Match | AK179: 1 row; exact match. | AL179: Rerun output matches supplied gold after ignoring row order and applying reference display precision. | AP179: 0.4 | AQ179: GeoQueryBench_Chaitanya_Error_Report_Reference_Style(1).xlsx
A180: Chaitanya | B180: NS2-024 | C180: NS | D180: NS-2 | E180: sql | F180: hard | G180: Combine both surface geochemistry sources (the main sample table and the WACHEM reference set) and report, per source, how many samples have gold above 100 ppb. | H180: 2 | I180: NS2-024.csv | K180: 2 | M180: Match | U180: Yes | AG180: Match | AI180: Independently rerun | AJ180: Match | AK180: 2 rows; exact match. | AL180: Rerun output matches supplied gold after ignoring row order and applying reference display precision. | AP180: 0 | AQ180: GeoQueryBench_Chaitanya_Error_Report_Reference_Style(1).xlsx
... A184: Chaitanya | B184: NS2-037 | C184: NS | D184: NS-2 | E184: geopandas | F184: medium | G184: Is the sampling evenly spread? For the Kalgoorlie box, give the distribution of sample counts across 5 km cells. | H184: 1 | I184: NS2-037.csv | K184: 1 | M184: Match | U184: Yes | AG184: Reference-only | AI184: Reference checked; not rerun | AJ184: Not independently compared | AK184: Not independently regenerated. | AL184: Reference file exists and its data-row count was checked against Expected Rows; query result was not independently regenerated. | AP184: 3.3 | AQ184: GeoQueryBench_Chaitanya_Error_Report_Reference_Style(1).xlsx
...
